[
  {
    "id": 1,
    "title": "Speaking",
    "artist": "Mrs.GREEN APPLE",
    "album": "Speaking",
    "release": "2015/12/16",
    "img": "./images/1.jpg",
    "popularity": 47561,
    "lyrics":{
      "japanese": [
        "ねえ {聞|き}かせて {君|きみ}の{好き|すき}な{歌|うた}は{何|なに}？",
        "ねえ {例|たと}えば {このまま|このまま}{何処|どこ}かへ{抜|ぬ}け出して",
        "{心臓|しんぞう}のblueを{隠|かく}さずに{話|はな}をしよう",
        "Yeah {起|お}きて{寝|ね}て {最高|さいこう}の日にしよう",
        "Well, おいでおいで {誰|だれ}もが{寂|さび}しくなったりするんだ",
        "{先生|せんせい}でも{何|なに}にも{知|し}らない",
        "{親友|しんゆう}でも{何|なに}にも{知|し}らない",
        "{誰|だれ}にも{話|はな}す気は{無|な}い？",
        "だけども{話|はな}してよ",
        "{曖昧|あいまい}な{態度|たいど}はいらない",
        "{哀|かなし}しみには{非|ひ}は{無|な}い",
        "{誰|だれ}にも{話|はな}す気は{無|な}い？",
        "だけども{話|はな}してよ",
        "{僕|ぼく}には{話|はな}してよ",
        "ねえ {聞|き}かせて {君|きみ}の{好き|すき}な{人|ひと}は{誰|だれ}？",
        "{この世界|このせかい}が{愛|あい}に{満|み}ちたらいいのにな",
        "{本能|ほんのう}のbluesを{隠|かく}さずに{叫|さけ}んでみてよ",
        "Hey {通|つう}じてみて {最高潮|さいこうちょう}で{居|い}よう",
        "Well, おいでおいで {誰|だれ}もが{独|ひと}りと{思|おも}ったりするんだ",
        "まだまだ{何|なに}にも{知|し}らない",
        "{君|きみ}はまだ{気付|きづ}けてない",
        "{誰|だれ}にも{話|はな}す気は{無|な}い？",
        "だけども{居|い}させてよ",
        "{曖昧|あいまい}な{態度|たいど}はいらない",
        "{哀|かなし}しみには{キリ|きり}が{無|な}い",
        "{誰|だれ}とも{話|はな}す気は{無|な}い？",
        "{僕|ぼく}には{話|はな}してよ",
        "{誰|だれ}かと{話|はな}してよ",
        "{愉快|ゆかい}に{朝|あさ}まで{踊|おど}りましょ",
        "{初|はじ}めての{キス|きす}を{謳|うた}いましょ",
        "{自|ご}自身の{趣味|しゅみ} or {特技|とくぎ}を",
        "{恥|は}ずかしがらずに{話|はな}そうよ",
        "でも{君|きみ}が{本当|ほんとう}に{知|し}りたいのは{誰|だれ}でもない「{君自身|きみじしん}」でしょう？",
        "{指先|ゆびさき}で{飛|と}ばすメッセージは",
        "{一体|いったい}{誰|だれ}の{何|なに}に{届|とど}いてるの",
        "「{教|おし}えなきゃ{転|ころ}んじゃう{様|よう}で",
        "{学|まな}ばなきゃ{怪我|けが}しちゃう{様|よう}です」",
        "{誰|だれ}も{知|し}らない{君|きみ}を",
        "{先生|せんせい}でも{何|なに}にも{知|し}らない",
        "{親友|しんゆう}でも{何|なに}にも{知|し}らない",
        "{誰|だれ}にも{話|はな}す気は{無|な}い？",
        "{大丈夫|だいじょうぶ}{話|はな}してよ",
        "{曖昧|あいまい}な{態度|たいど}はいらない",
        "{遊|あそ}ぼう{飛|と}ぼう",
        "{誰|だれ}にも{話|はな}す気は{無|な}い？",
        "だけども{話|はな}してよ",
        "{僕|ぼく}には{教|おし}えてよ"
      ],
      "chinese": [
        "喂，告訴我，你喜歡的歌是什麼？",
        "喂，比方說，就這樣溜出去吧",
        "讓我們聊聊，不再隱藏內心的憂鬱",
        "Yeah，醒來睡去，讓今天成為最棒的一天吧",
        "Well，來吧來吧，誰都會感到孤單",
        "即使是老師也一無所知",
        "即使是摯友也一無所知",
        "不打算和任何人說嗎？",
        "但還是告訴我吧",
        "不需要曖昧的態度",
        "悲傷沒有錯",
        "不打算和任何人說嗎？",
        "但還是告訴我吧",
        "告訴我吧",
        "喂，告訴我，你喜歡的人是誰？",
        "要是這個世界充滿愛就好了",
        "試著無所顧忌地喊出本能的憂鬱吧",
        "Hey，讓彼此相通，處於最高潮",
        "Well，來吧來吧，誰都會覺得自己是孤單一人",
        "我們還有很多事不知道",
        "你還沒有意識到",
        "不打算和任何人說嗎？",
        "但讓我留在身邊吧",
        "不需要曖昧的態度",
        "悲傷是無窮無盡的",
        "不打算和任何人說嗎？",
        "但告訴我吧",
        "和誰聊聊吧",
        "開心地跳舞到天亮吧",
        "歌頌初吻吧",
        "你的興趣或特長",
        "別害羞，和我聊聊吧",
        "但是你真正想知道的，應該是你自己吧？",
        "指尖傳出的信息",
        "究竟傳到了誰的心裡",
        "「若不教你，你會摔跤",
        "若不學習，你會受傷」",
        "誰也不知道的你",
        "即使是老師也一無所知",
        "即使是摯友也一無所知",
        "不打算和任何人說嗎？",
        "沒關係，告訴我吧",
        "不需要曖昧的態度",
        "讓我們遊玩起來，飛翔起來",
        "不打算和任何人說嗎？",
        "但還是告訴我吧",
        "告訴我吧"
      ]
    }
  },
  {
    "id": 2,
    "title": "WanteD! WanteD!",
    "artist": "Mrs.GREEN APPLE",
    "album": "WanteD! WanteD!",
    "release": "2017/8/30",
    "img": "./images/2.jpg",
    "popularity": 35001,
    "lyrics":{
      "japanese": [
        "{だんだん|だんだん}{簡単|かんたん}に{心|こころ}が{壊|こわ}れてしまうようになったな",
        "{やる気|やるき}{捥|も}がれて{傷|きず}ついたから",
        "「{あぁ|あぁ}{もう|もう}{辞|や}めだ」",
        "Wow, WanteD! WanteD!",
        "{僕|ぼく}らは{逃|に}げている",
        "Wow, WanteD! WanteD!",
        "{自分|じぶん}の{弱|よわ}さから",
        "{お馬鹿|おばか}な{振|ふ}りをして",
        "{ゆらゆら|ゆらゆら}{生|い}きている",
        "{誰|だれ}も{知|し}らない",
        "{僕|ぼく}らの{行|い}き{先|さき}は",
        "Wow, wow, wow, wow",
        "{だんだん|だんだん}{快感|かいかん}になってきたよ",
        "{ツマラヌ|つまらぬ} {オトナドモ|おとなども}",
        "{気高|けだか}く{保守的|ほしゅてき}なだけね",
        "でもとりあえず{踊|おど}りましょう",
        "{グチャグチャ|ぐちゃぐちゃ}{絵|え}の{具|ぐ}で{彩|いろど}って",
        "{ムチャムチャ|むちゃむちゃ}な{夜|よる}と{絡|から}まって",
        "I don't wanna do {愛|あい}の{罠|わな}よ",
        "まぁ I don't care",
        "Wow, WanteD! WanteD!",
        "{僕|ぼく}らは{逃|に}げている",
        "Wow, WanteD! WanteD!",
        "{妬|ねた}む{心|こころ}から",
        "あの{子|こ}は{馬鹿|ばか}で",
        "{スラスラ|すらすら}{生|い}きれている",
        "「{月|つき}が{綺麗|きれい}だ」",
        "{幸|しあわ}せの{形|かたち}を",
        "{何|なに}かの{所為|せい}にして",
        "{遊|あそ}べるのは{今|いま}だけなんだ",
        "{焦|あせ}らなくていい？",
        "{少|すこ}しずつ{気付|きづ}いてゆけばいい？",
        "Wow, WanteD! WanteD!",
        "{僕|ぼく}らは{生|い}きている",
        "Wow, WanteD! WanteD!",
        "{間違|まちが}いながらも",
        "{逃|に}げるのに{慣|な}れて",
        "{愛|あい}に{気付|きづ}けなくなっている",
        "{何時|いつ}か{綺麗|きれい}な",
        "{大人|おとな}になれるかな",
        "Wow, WanteD! WanteD!",
        "Wow, WanteD! WanteD!",
        "Wow, wow, wow, wow"
      ],
      "chinese": [
        "漸漸地，感覺心變得容易崩壞了",
        "因為失去了幹勁而受傷了",
        "「啊，算了，不幹了」",
        "Wow, WanteD! WanteD!",
        "我們正在逃跑",
        "Wow, WanteD! WanteD!",
        "逃避自己的脆弱",
        "假裝傻傻的",
        "搖搖晃晃地活著",
        "沒人知道",
        "我們的去向",
        "Wow, wow, wow, wow",
        "漸漸地變成了快感",
        "無聊的大人們",
        "只是不斷保持著驕傲和保守",
        "不過還是先跳舞吧",
        "用亂七八糟的顏料裝點",
        "與混亂的夜晚糾纏在一起",
        "我不想陷入愛情的陷阱",
        "嘛，我不在乎",
        "Wow, WanteD! WanteD!",
        "我們正在逃跑",
        "Wow, WanteD! WanteD!",
        "從嫉妒的心逃避",
        "那個傻孩子",
        "輕輕鬆鬆地活著",
        "「月亮真美」",
        "將幸福的形狀",
        "歸咎於某種原因",
        "能玩耍的只有現在",
        "不需要著急嗎？",
        "慢慢地發現就好了嗎？",
        "Wow, WanteD! WanteD!",
        "我們正在活著",
        "Wow, WanteD! WanteD!",
        "即使不斷犯錯",
        "已經習慣於逃避",
        "對愛已經感覺不到了",
        "總有一天能成為",
        "美好的大人嗎",
        "Wow, WanteD! WanteD!",
        "Wow, WanteD! WanteD!",
        "Wow, wow, wow, wow"
      ]
    }    
  },
  {
    "id": 3,
    "title": "春愁",
    "artist": "Mrs.GREEN APPLE",
    "album": "Love me, Love you",
    "release": "2018/2/14",
    "img": "./images/3.jpg",
    "popularity": 17196,
    "lyrics":{
      "japanese": [
        "「{早|はや}いものね」と{心|こころ}が{囁|ささや}いた",
        "{言|い}われてみれば「うん、{早|はや}かった。」",
        "{又|また}{昨日|きのう}と{同|おな}じ{今日|きょう}を{過|す}ごした",
        "そんなことばっか{繰|く}り{返|かえ}してた",
        "「{憧|あこが}れ」「{理想|りそう}」と たまに{喧嘩|けんか}をした",
        "{どうしても|どうしても}{仲良|なかよ}くなれなかった",
        "{青|あお}さの{カケラ|かけら}が{行|い}き{交|か}うが",
        "やっぱり{摘|つ}み{取|と}ることは{出来|でき}なかった",
        "{大嫌|だいきら}いだ",
        "{人|ひと}が{大嫌|だいきら}いだ",
        "{友達|ともだち}も{大嫌|だいきら}いだ",
        "{本当|ほんとう}は{大好|だいす}きだ",
        "{明日|あした}が{晴|は}れるなら それでいいや",
        "{明日|あした}が{来|く}るのなら それでいいや",
        "{あなた|あなた}が{笑|わら}うなら なんでもいいや",
        "{世界|せかい}は{変|か}わりゆくけど それだけでいいや",
        "「{ありがたい|ありがたい}ね」と{心|こころ}が{囁|ささや}いた",
        "{言|い}われずとも ちゃんと{解|わ}かっていた",
        "{又|また}{昨日|きのう}と{同|おな}じ{今日|きょう}を{過|す}ごした",
        "そんなことばっかり{思|おも}ってた",
        "「{涙|なみだ}」や「{笑|わら}い」も{少|すく}なかったりした",
        "{実|じつ}はそんなこともなかった",
        "{春|はる}が{息吹|いぶ}く {桜|さくら}の{花|はな}も{舞|ま}いはせず",
        "{只|ただ}{陽|ひ}に{照|て}らされていた",
        "{大嫌|だいきら}いだ",
        "{今日|きょう}が{大嫌|だいきら}いだ",
        "{昨日|きのう}も{大嫌|だいきら}いだ",
        "{明日|あした}が{大好|だいす}きだ",
        "{何時|いつ}か {何時|いつ}か {見|み}つけてくれるのなら",
        "{何時|いつ}か {何時|いつ}か {大切|たいせつ}に{思|おも}えるなら",
        "{あなた|あなた}が{生|い}きてさえいれば なんでもいいや",
        "{わたし|わたし}が{生|い}きてるなら それでいいや",
        "それがいいや",
        "それがいいや",
        "{大嫌|だいきら}いだ",
        "{人|ひと}が{大嫌|だいきら}いだ",
        "{友達|ともだち}も{大嫌|だいきら}いだ",
        "{本当|ほんとう}は{大好|だいす}きだ"
      ],
      "chinese": [
        "「時間過得真快啊」心裡這麼低語著",
        "仔細想想「嗯，是挺快的。」",
        "又度過了和昨天一樣的今天",
        "這種事情一直在重複",
        "和「憧憬」和「理想」偶爾會吵架",
        "怎麼也無法和它們好好相處",
        "一片片的青春交錯而過",
        "但果然還是無法摘下它",
        "我討厭",
        "討厭人類",
        "也討厭朋友",
        "其實我真的很喜歡",
        "如果明天是晴天，那就夠了",
        "如果明天會來，那就足夠了",
        "只要你能笑，什麼都可以",
        "即使世界在變化，這樣就足夠了",
        "「真感激啊」心裡這麼低語著",
        "不說也明白",
        "又度過了和昨天一樣的今天",
        "我一直這麼想著",
        "「淚水」和「笑容」都變少了",
        "其實也並不是那麼少",
        "春天蘇醒了，櫻花也沒有飄落",
        "只是被陽光照耀著",
        "我討厭",
        "討厭今天",
        "也討厭昨天",
        "但我愛明天",
        "如果有一天能找到我",
        "如果有一天能珍惜我",
        "只要你還活著，什麼都可以",
        "只要我還活著，那就夠了",
        "這樣就好",
        "這樣就好",
        "我討厭",
        "討厭人類",
        "也討厭朋友",
        "其實我真的很喜歡"
      ]
    }    
  },
  {
    "id": 4,
    "title": "青と夏",
    "artist": "Mrs.GREEN APPLE",
    "album": "青と夏",
    "release": "2018/8/1",
    "img": "./images/4.jpg",
    "popularity": 54626,
    "lyrics":{
      "japanese": [
        "{涼|すず}しい{風|かぜ}{吹|ふ}く {青空|あおぞら}の{匂|にお}い",
        "{今日|きょう}はダラッと{過|す}ごしてみようか",
        "{風鈴|ふうりん}がチリン {向日葵|ひまわり}の{黄|き}いろ",
        "{私|わたし}には{関係|かんけい}ないと{思|おも}って{居|い}たんだ",
        "{夏|なつ}が{始|はじ}まった{合図|あいず}がした",
        "「{傷|きず}つき{疲|つか}れる」けどもいいんだ",
        "{次|つぎ}の{恋|こい}の{行方|ゆくえ}はどこだ",
        "{映画|えいが}じゃない {主役|しゅやく}は{誰|だれ}だ",
        "{映画|えいが}じゃない {僕|ぼく}らの{番|ばん}だ",
        "{優|やさ}しい{風|かぜ}{吹|ふ}く {夕焼|ゆうや}けの「またね」",
        "{分|わ}かっているけど{何時|いつ}か{終|お}わる",
        "{風鈴|ふうりん}がチリン スイカの{種|たね}{飛|と}ばし",
        "{私|わたし}にも{関係|かんけい}あるかもね",
        "{友達|ともだち}の{嘘|うそ}も {転|ころ}がされる{愛|あい}も",
        "{何|なに}から{信|しん}じていいんでしょうね",
        "{大人|おとな}になってもきっと",
        "{宝物|たからもの}は{褪|あ}せないよ",
        "{大丈夫|だいじょうぶ}だから {今|いま}はさ",
        "{青|あお}に{飛|と}び{込|こ}んで{居|い}よう",
        "{夏|なつ}が{始|はじ}まった {恋|こい}に{落|お}ちた",
        "もう{待|ま}ち{疲|つか}れたんだけど、どうですか？？",
        "{本気|ほんき}になればなるほど{辛|つら}い",
        "{平和|へいわ}じゃない {私|わたし}の{恋|こい}だ",
        "{私|わたし}の{恋|こい}だ",
        "{寂|さび}しいな やっぱ{寂|さび}しいな",
        "{何時|いつ}か{忘|わす}れられてしまうんだろうか",
        "それでもね「{繋|つな}がり」{求|もと}める",
        "{人|ひと}の{素晴|すば}らしさを{信|しん}じてる",
        "{運命|うんめい}が{突|つ}き{動|うご}かされてゆく",
        "{赤|あか}い{糸|いと}が{音|おと}を{立|た}てる",
        "{主役|しゅやく}は{貴方|あなた}だ",
        "{夏|なつ}が{始|はじ}まった {君|きみ}はどうだ",
        "{素直|すなお}になれる{勇気|ゆうき}はあるか",
        "{この恋|このこい}の{行方|ゆくえ}はどこだ",
        "{映画|えいが}じゃない {愛|いと}しい{日々|ひび}だ",
        "{恋|こい}が{始|はじ}まった{合図|あいず}がした",
        "{今日|きょう}を{待|ま}ちわびた なんて{良|い}い{日|ひ}だ",
        "{未|まだ}{未|まだ}{終|お}われないこの{夏|なつ}は",
        "{映画|えいが}じゃない {君|きみ}らの{番|ばん}だ",
        "{映画|えいが}じゃない {僕|ぼく}らの{青|あお}だ",
        "{映画|えいが}じゃない {僕|ぼく}らの{夏|なつ}だ"
      ],
      "chinese": [
        "涼爽的風吹來，藍天的氣息",
        "今天要不要懶懶地度過呢",
        "風鈴叮噹作響，向日葵的黃色",
        "我以為這些和我無關",
        "夏天開始了的信號響起了",
        "「受傷、疲憊」但也沒關係",
        "下一段戀愛的去向在哪裡",
        "這不是電影，誰是主角",
        "這不是電影，輪到我們了",
        "溫柔的風輕吹，「再見」在夕陽下",
        "我明白，總有一天會結束",
        "風鈴叮噹作響，西瓜的種子飛了出去",
        "也許這些也和我有關呢",
        "朋友的謊言和被玩弄的愛情",
        "到底該相信什麼才好呢",
        "即使長大了",
        "寶物也不會褪色",
        "沒關係的",
        "現在就跳進藍色裡吧",
        "夏天開始了，我戀愛了",
        "雖然已經等得有些疲倦了，你覺得呢？？",
        "越是認真越是痛苦",
        "這不是和平，我的戀愛",
        "這是我的戀愛",
        "好寂寞啊，果然還是寂寞啊",
        "總有一天會被忘記吧",
        "即便如此，還是想尋找「聯繫」",
        "我相信人類的美好",
        "命運開始運轉",
        "紅線發出了聲響",
        "主角是你",
        "夏天開始了，你怎麼樣",
        "你有變得坦率的勇氣嗎",
        "這段戀情的去向在哪裡",
        "這不是電影，是珍貴的日子",
        "戀愛開始了的信號響起了",
        "期待已久的今天，真是美好的一天",
        "這個夏天還沒結束",
        "這不是電影，輪到你們了",
        "這不是電影，這是我們的藍天",
        "這不是電影，這是我們的夏天"
      ]
    }   
  },
  {
    "id": 5,
    "title": "点描の唄(feat.井上苑子)",
    "artist": "Mrs.GREEN APPLE",
    "album": "青と夏",
    "release": "2018/8/1",
    "img": "./images/5.jpg",
    "popularity": 3701,
    "lyrics":{
      "japanese": [
        "{貴方|あなた}の{声|こえ}で{解|ほぐ}れてゆく",
        "{忘|わす}れたくないと{心|こころ}が{云|い}う",
        "{思|おも}い{出|で}ばっか{増|ふ}えてゆく",
        "ずっと{側|そば}に{居|い}たい",
        "{泣|な}き{虫|むし}でもいいかな",
        "{強|つよ}がらないでいいよ",
        "{限|かぎ}りある{恋|こい}だとしても",
        "{出逢|であ}えて{幸|しあわ}せです",
        "{何時|いつ}までも {何時|いつ}までも",
        "{続|つづ}いて{欲|ほ}しいと{願|ねが}っている",
        "{手|て}を{取|と}ることは{出来|でき}ずとも",
        "{私|わたし}は{貴方|あなた}を{好|す}いている",
        "{貴方|あなた}の{夢|ゆめ}で{心|こころ}{安|やす}らぐ",
        "{目覚|めざ}めたくないと{僕|ぼく}は{云|い}う",
        "{思|おも}い{出|で}ばっか{増|ふ}えてゆく",
        "{明日|あした}も{側|そば}に{居|い}たい",
        "{何処|どこ}までも {何処|どこ}までも",
        "{鈍感|どんかん}な{僕|ぼく}を{叱|しか}って{欲|ほ}しい",
        "{当|あ}たり{前|まえ}が{壊|こわ}れることに",
        "{気付|きづ}けないくらいに{子供|こども}だけど",
        "{ちゃんと|ちゃんと}{僕|ぼく}は{貴方|あなた}を{好|す}いている",
        "{私|わたし}の{僕|ぼく}の",
        "{時間|じかん}が{止|と}まればいいのに",
        "ほらまた{期待|きたい}をしてしまう",
        "グッと{堪|こら}えてみるからさ",
        "{若|もし}{溢|あふ}れ{出|だ}したら",
        "{瞳|ひとみ}を{ちゃんと|ちゃんと}{見|み}てよ　{見|み}てよ　{見|み}て",
        "{貴方|あなた}の{影|かげ}だけ{伸|の}びてゆく",
        "{消|き}えてしまわないで",
        "ずっと　この{思|おも}いは{変|か}わらない",
        "{何時|いつ}までも {何時|いつ}までも",
        "{続|つづ}いて{欲|ほ}しいと{願|ねが}っている",
        "{手|て}を{取|と}ることは{出来|でき}ずとも",
        "{過|す}ぎていく{現在|いま}に{抱|だ}きしめられている",
        "{私|わたし}の{僕|ぼく}の",
        "{時間|じかん}が{止|と}まればいいのに",
        "{今日|きょう}を{噛|かみ}{締|し}めていよう",
        "{終|お}わるな",
        "{夏|なつ}よ、{終|お}わるな"
      ],
      "chinese": [
        "因為你的聲音而平靜下來",
        "心說不想忘記",
        "回憶越來越多",
        "我想一直在你身邊",
        "即使是愛哭鬼也可以吧",
        "不用再逞強了",
        "即使這段戀情是有限的",
        "能遇見你真是幸福",
        "永遠，永遠",
        "希望這一切能夠延續",
        "即使無法牽手",
        "我也依然喜歡著你",
        "在你的夢裡，心變得安寧",
        "我說我不想醒來",
        "回憶越來越多",
        "明天也想和你在一起",
        "無論多遠，無論多遠",
        "希望你責備這樣遲鈍的我",
        "對於理所當然的事物崩壞",
        "我無法察覺，因為還只是個孩子",
        "但我確實喜歡著你",
        "我的、你的",
        "時間能停下來該有多好",
        "看吧，我又期待了",
        "努力忍耐著",
        "如果情感滿溢而出",
        "請好好看著我的眼睛，看著我，看著我",
        "只有你的影子越拉越長",
        "請不要消失",
        "這份感情永遠不會改變",
        "永遠，永遠",
        "希望這一切能夠延續",
        "即使無法牽手",
        "現在這一刻也被擁抱著",
        "我的、你的",
        "時間能停下來該有多好",
        "咬緊牙關感受今天",
        "不要結束",
        "夏天啊，不要結束"
      ]
    }
  },
  {
    "id": 6,
    "title": "僕のこと",
    "artist": "Mrs.GREEN APPLE",
    "album": "僕のこと",
    "release": "2019/1/9",
    "img": "./images/6.jpg",
    "popularity": 32102,
    "lyrics":{
      "japanese": [
        "{僕|ぼく}と{君|きみ}とでは{何|なに}が{違|ちが}う?",
        "おんなじ{生|い}き{物|もの}さ {分|わ}かってる",
        "でもね {僕|ぼく}は{何|なに}かに{怯|おび}えている",
        "{皆|みんな}もそうならいいな",
        "{がむしゃら|がむしゃら}に{生|い}きて{誰|だれ}が{笑|わら}う?",
        "{悲|かな}しみきるには{早|はや}すぎる",
        "いつも{僕|ぼく}は{自分|じぶん}に{言|い}い{聞|き}かせる",
        "{明日|あした}もあるしね",
        "ああ {何|なん}て{素敵|すてき}な{日|ひ}だ",
        "{幸|しあわ}せと{思|おも}える{今日|きょう}も {夢|ゆめ}{敗|やぶ}れ{挫|くじ}ける{今日|きょう}も",
        "ああ {諦|あきら}めず{足搔|もが}いている",
        "{狭|せま}い{広|ひろ}い{世界|せかい}で {奇跡|きせき}を{唄|うた}う",
        "{僕|ぼく}らは{知|し}っている {空|そら}への{飛|と}び{方|かた}も",
        "{大人|おとな}になるにつれ{忘|わす}れる",
        "{限|かぎ}りある{永遠|えいえん}も {治|なお}りきらない{傷|きず}も",
        "{全|すべ}て{僕|ぼく}のこと {今日|きょう}という{僕|ぼく}のこと",
        "{得|え}ては{失|うしな}う{日々|ひび} {意味|いみ}はある?",
        "{伝|つた}わることのない{想|おも}いもある",
        "だから{僕|ぼく}は{時々|ときどき}{寂|さび}しくなる",
        "{皆|みんな}もそうなら {少|すこ}しは{楽|らく}かな",
        "{僕|ぼく}だけじゃないと {思|おも}えるかな",
        "ああ {何|なん}て{素敵|すてき}な{日|ひ}だ",
        "{誰|だれ}かを{好|す}きでいる{今日|きょう}も {頬|ほお}{濡|ぬ}らし{眠|ねむ}れる{今日|きょう}も",
        "ああ {嘆|なげ}くにはほど{遠|とお}い",
        "{狭|せま}い{広|ひろ}い{世界|せかい}で {僕|ぼく}らは{唄|うた}う",
        "{冬|ふゆ}に{咲|さ}く{花|はな}に {命|いのち}が{芽吹|めぶ}くよ",
        "{駆|か}けるは {雪|ゆき}の{大地|だいち}",
        "{青|あお}すぎた{春|はる}を {忘|わす}れずに{居|い}たいと",
        "{語|かた}るは {友|とも}との{地図|ちず}",
        "{駆|か}けるは {人|ひと}の{旅路|たびじ}",
        "{僕|ぼく}らは{知|し}っている {奇跡|きせき}は{死|し}んでいる",
        "{努力|どりょく}も{孤独|こどく}も {報|むく}われないことがある",
        "だけどね それでもね {今日|きょう}まで{歩|ある}いてきた",
        "{日々|ひび}を{人|ひと}は{呼|よ}ぶ それがね {軌跡|きせき}だと",
        "ああ {何|なん}て{素敵|すてき}な{日|ひ}だ",
        "{幸|しあわ}せに{悩|なや}める{今日|きょう}も {ボロボロ|ぼろぼろ}になれている{今日|きょう}も",
        "ああ {息|いき}をして{足搔|もが}いている",
        "{全|すべ}て{僕|ぼく}のこと あの{日|ひ}の{僕|ぼく}らのこと",
        "{僕|ぼく}と{君|きみ}とでは{何|なに}が{違|ちが}う?",
        "それぞれ{見|み}てきた{景色|けしき}がある",
        "{僕|ぼく}は{僕|ぼく}として いまを{生|い}きてゆく",
        "とても{愛|いと}しい{事|こと}だ"
      ],
      "chinese": [
        "我和你有什麼不同？",
        "都是一樣的生物，我明白的",
        "但是啊，我對某些東西感到害怕",
        "如果大家也一樣的話就好了",
        "拼命地活著，誰會嘲笑？",
        "悲傷還為時過早",
        "我總是對自己說",
        "反正還有明天",
        "啊，真是美好的一天",
        "覺得幸福的今天，夢想破滅挫折的今天",
        "啊，不放棄地掙扎著",
        "在狹窄又寬廣的世界中，歌唱著奇蹟",
        "我們知道如何飛向天空",
        "隨著成長卻逐漸忘記",
        "有限的永遠，治癒不完的傷痕",
        "都是我的事，今日的我",
        "得而復失的日子，有意義嗎？",
        "有些情感無法傳達",
        "因此我有時會感到寂寞",
        "如果大家也一樣，會輕鬆一點嗎",
        "能感到不只是我一個人嗎",
        "啊，真是美好的一天",
        "喜歡著某人的今天，淚濕臉頰入睡的今天",
        "啊，還不足以嘆息",
        "在狹窄又寬廣的世界中，我們歌唱",
        "冬天綻放的花朵，生命在萌芽",
        "奔馳在白雪覆蓋的大地上",
        "想要不忘過於青澀的春天",
        "講述的是與朋友的地圖",
        "奔馳在人們的旅途上",
        "我們知道奇蹟已死",
        "努力與孤獨，有時無法得到回報",
        "儘管如此，走到了今天",
        "人們稱之為日子，那就是軌跡",
        "啊，真是美好的一天",
        "為幸福而煩惱的今天，滿身創傷的今天",
        "啊，呼吸著掙扎著",
        "都是關於我的事，關於那天的我們",
        "我和你有什麼不同？",
        "各自看過的風景有所不同",
        "我作為我，將活在當下",
        "這是多麼令人愛惜的事啊"
      ]
    }
    
  },
  {
    "id": 7,
    "title": "ANTENNA",
    "artist": "Mrs.GREEN APPLE",
    "album": "ANTENNA",
    "release": "2023/7/5",
    "img": "./images/7.jpg",
    "popularity": 16635,
    "lyrics":{
      "japanese": [
        "Boys and girls",
        "{妄想|もうそう}は{当然|とうぜん}だ",
        "{良|よ}し{悪|あ}しじゃない{好|す}きな{方角|ほうがく}",
        "{何|ど}れもが{奇跡|きせき} {君|きみ}だけのその{世界|せかい}",
        "{愛|あい}してるよ ホープレス",
        "「{満|み}ち{足|た}らない」こそね",
        "{分|わ}かりはしないから いつも",
        "ドキドキしていれるんでしょう?",
        "アンテナコントロールして",
        "{憂鬱|ゆううつ}も{抱|だ}きしめて",
        "{何処|どこ}までも{行|い}ける そんな{気|き}がしてる",
        "{少|すこ}しずつと{変|か}わる{人|ひと}や{季節|きせつ}に{疲|つか}れてしまうけど",
        "{私|わたし}が{私|わたし}{自身|じしん}を{諦|あきら}めて{痛|いた}みに{気|き}づけない {未来|みらい}がただ{怖|こわ}い",
        "{愛|あい}してるの? {どう|どう}りで",
        "{見失|みうしな}うばっかりで",
        "{測|はか}れはしない{幸福|こうふく}の",
        "{意味付|いみづ}けをしてるんでしょう?",
        "アンテナコントロールして",
        "{古傷|ふるきず}も{抱|だ}きしめて",
        "{何処|どこ}までも{戻|もど}れる そんな{気|き}がしてる",
        "{感|かん}じ{取|と}った? {理|ことわり}の{電波|でんぱ}",
        "{受|う}け{取|と}った? {私|わたし}の{愛|あい}は",
        "{間違|まちが}ったことなんて{無|な}いわ",
        "{君|きみ}だけの{存在|そんざい}の{周波|しゅうは}",
        "{遣|や}り{直|なお}したい{過去|かこ}は{無|な}いけど{謝|あやま}れたら{良|い}いな",
        "{過|す}ぎ{去|さ}ったものは{戻|もど}らないけど{今日|きょう}を{生|い}きる{私|わたし}の{銀河|ぎんが}",
        "{愛|あい}を{捨|す}てるの? {本気|ほんき}で?",
        "{疲|つか}れてしまったの?",
        "アンテナは{動|うご}いてる",
        "{私|わたし}たちは{生|い}きている",
        "{何|なに}をしていても{変|か}わらない{真実|しんじつ}です",
        "{愛|あい}してるよ ホープレス",
        "{数知|かずし}れない{交差|こうさ}で",
        "{未|まだ}{見|み}ぬ{景色|けしき}にドキドキ{出|で}きるんでしょう?",
        "アンテナコントロールして",
        "{全|すべ}てを{抱|だ}きしめて",
        "{何処|どこ}までも{行|い}ける そんな{気|き}がしてる"
      ],
      "chinese": [
        "男孩和女孩們",
        "妄想是理所當然的",
        "不論好壞，選擇喜歡的方向",
        "一切都是奇蹟，只有你擁有的那個世界",
        "我愛著你，無望的愛",
        "「正因為不滿足」才會這樣",
        "無法完全理解，所以才總是",
        "能心跳加速，不是嗎？",
        "控制著天線",
        "擁抱憂鬱",
        "感覺能去到任何地方",
        "雖然逐漸被變化中的人與季節弄得疲憊",
        "如果我放棄了自己，無法感知痛苦，未來令人害怕",
        "愛著嗎？怪不得",
        "總是迷失自己",
        "難以衡量的幸福",
        "在為它賦予意義，不是嗎？",
        "控制著天線",
        "擁抱著舊傷",
        "感覺可以回到任何地方",
        "感受到了嗎？理性的電波",
        "收到了嗎？我的愛",
        "從未錯誤",
        "只有你的存在的頻率",
        "雖然沒有想過重來，但若能道歉就好了",
        "過去的事無法回溯，但在今天活著的我自己的銀河",
        "你要捨棄愛嗎？真的嗎？",
        "已經疲憊了嗎？",
        "天線在運作",
        "我們活著",
        "不論做什麼都無法改變的真實",
        "我愛著你，無望的愛",
        "無數交錯中",
        "能因未曾見過的風景而心動，不是嗎？",
        "控制著天線",
        "擁抱一切",
        "感覺能去到任何地方"
      ]
    }
  },
  {
    "id": 8,
    "title": "Soranji",
    "artist": "Mrs.GREEN APPLE",
    "album": "Soranji",
    "release": "2022/11/9",
    "img": "./images/8.jpg",
    "popularity": 49570,
    "lyrics":{
      "japanese": [
        "{貴方|あなた}に{会|あ}いたくて",
        "{生|う}まれてきたんだよ",
        "{今|いま} {伝|つた}えたいんだよ",
        "{私|わたし}はただ",
        "{私|わたし}はまだ",
        "{始|はじ}まりの{朝|あさ}が{来|く}る",
        "{宝物|たからもの}を{探|さが}すけど",
        "{何時|いつ}の{間|ま}にか すぐ{側|そば}にある{事|こと}を",
        "{忘|わす}れて{今日|きょう}も{浮|う}かんでます",
        "{思|おも}い{出|で}は{歩|ある}いてきた{証|あかし}だと",
        "この{傷|きず}が{教|おし}えてくれる",
        "{当|あ}たり{前|まえ}に{進|すす}んでゆく{皆|みんな}に",
        "{付|つ}いて{行|い}こうと{頑張|がんば}っています",
        "{汚|よご}れながら{泳|およ}ぐ{生|せい}の{中|なか}で",
        "まあ よくぞここまで{大事|だいじ}にして",
        "{抱|かか}えて{来|こ}れましたね",
        "{未|まだ}{消|き}えちゃいないよ",
        "ちっちゃな{希望|きぼう}を",
        "{何|なん}とか{信|しん}じて",
        "{信|しん}じて{欲|ほ}しい",
        "{裏切|うらぎ}りが{続|つづ}こうが",
        "「{大切|たいせつ}」が{壊|こわ}れようと",
        "{何|なん}とか{生|い}きて",
        "{生|い}きて{欲|ほ}しい",
        "{有|あり}{得|え}ないほどに",
        "キリがない{本当|ほんとう}に",
        "{無駄|むだ}がないほどに",
        "{我|われ}らは{尊|とうと}い",
        "{寂|さび}しさの{甲斐|かい}はない",
        "{雪|ゆき}も{何時|いつ}かは{溶|と}けるけど",
        "{鳥|とり}の{群|む}れは{明日|あした}へと{飛|と}び{立|た}つが",
        "{私|わたし}は{今日|きょう}も{小|ちい}さくなってます",
        "{揺|ゆ}らり{揺|ゆ}れながら",
        "{産声|うぶごえ}が{聞|き}こえる",
        "{繰|く}り{返|かえ}してる{春|はる}",
        "{大事|だいじ}にして{語|かた}り{継|つ}いでくれましたか?",
        "{未|まだ}{伝|つた}えてないよ",
        "{今日|きょう}の{分|ぶん}の「{大好|だいす}き」を",
        "{未来|みらい}でも{変|か}わらず{届|とど}けられますように",
        "この{世|よ}が{終|お}わるその{日|ひ}に",
        "{明日|あした}の{予定|よてい}を{立|た}てよう",
        "そうやって{生|い}きて",
        "{生|い}きてみよう",
        "{有|あり}{得|え}ないほどに",
        "キリがない{本当|ほんとう}に",
        "{無駄|むだ}がないほどに",
        "{我|われ}らは{尊|とうと}い",
        "{踏|ふ}み{締|し}める{大地|だいち}に",
        "{重|かさ}なるはアイロニー",
        "{有|あり}{得|え}ないほどに",
        "キリがない{本当|ほんとう}に",
        "{未|まだ}{消|け}しちゃいけないよ",
        "ちっちゃな{希望|きぼう}を",
        "{迷|まよ}わず{信|しん}じて",
        "{信|しん}じて{欲|ほ}しい",
        "{暗闇|くらやみ}が{続|つづ}こうと",
        "{貴方|あなた}を{探|さが}していたい",
        "だから{生|い}きて",
        "{生|い}きてて{欲|ほ}しい",
        "{有|あり}{得|え}ないほどに",
        "キリがない{本当|ほんとう}に",
        "{目|め}くるめく{世界|せかい}に",
        "{膝|ひざ}を{抱|かか}えていたり",
        "{誰|だれ}しも{何処|どこ}かに",
        "{弱|よわ}さがある{様|よう}に",
        "{無駄|むだ}がないほどに",
        "{我|われ}らは{尊|とうと}い",
        "{一歩|いっぽ}ずつでいいからさ",
        "{何気|なにげ}ない{今日|きょう}をただ{愛|あい}して{欲|ほ}しい",
        "ズタズタになった{芯|しん}もほら",
        "{明日|あした}へと{花|はな}を{咲|さ}かすから",
        "{繋|つな}いで{欲|ほ}しい"
      ],
      "chinese": [
        "為了見到你",
        "我才誕生的",
        "現在想傳達的是",
        "我只是",
        "我還在",
        "迎接全新的早晨",
        "尋找寶物",
        "但不知不覺間，它就在身邊",
        "今天也飄浮著",
        "回憶是我曾經走過的證明",
        "這道傷告訴了我",
        "所有正常向前的人們",
        "我正在努力跟隨",
        "在沾染塵埃的生命中游泳",
        "竟能這麼珍惜走到這裡",
        "一直攜帶著",
        "還沒有消失哦",
        "小小的希望",
        "努力地相信",
        "希望你也能相信",
        "即使背叛繼續",
        "即使「珍惜」崩壞",
        "努力活著",
        "希望你能活下去",
        "難以置信的程度",
        "真的是無止盡",
        "無比珍貴的",
        "我們是無比尊貴的",
        "寂寞無所依",
        "雪總有一天會融化",
        "鳥群將飛向明日",
        "而我今天也變得渺小",
        "搖晃著",
        "聽見了生命的誕生",
        "不斷重複的春天",
        "被珍視並傳承下去了嗎?",
        "還沒傳達哦",
        "今天份的「最愛你」",
        "希望未來也能不變地傳遞",
        "在這世界結束的那天",
        "計劃明天的行程",
        "就這樣活著",
        "試著活下去",
        "難以置信的程度",
        "真的是無止盡",
        "無比珍貴的",
        "我們是無比尊貴的",
        "踩在腳下的大地上",
        "交疊著的是諷刺",
        "難以置信的程度",
        "真的是無止盡",
        "還不能消失哦",
        "小小的希望",
        "毫不猶豫地相信",
        "希望你也能相信",
        "即使黑暗持續",
        "我還想尋找你",
        "所以請活下去",
        "希望你能活下去",
        "難以置信的程度",
        "真的是無止盡",
        "在瞬息萬變的世界中",
        "擁抱著膝蓋",
        "無論誰都在某處",
        "都有軟弱之處",
        "無比珍貴的",
        "我們是無比尊貴的",
        "只需一步一步",
        "請珍愛這平凡的今天",
        "看啊，即便殘破不堪的內心",
        "也會在明日綻放花朵",
        "希望你能牽起"
      ]
    }
  },
  {
    "id": 9,
    "title": "ニュー・マイ・ノーマル",
    "artist": "Mrs.GREEN APPLE",
    "album": "Unity",
    "release": "2022/7/8",
    "img": "./images/9.jpg",
    "popularity": 83506,
    "lyrics":{
      "japanese": [
        "エンドレス {鳴|な}り{止|や}まない",
        "{酸|す}いも{甘|あま}いも{引|ひ}っ{掻|か}き{傷|きず}も{愛|あい}して",
        "{足|た}りない{何|なに}かを{今|いま}も{待|ま}ち{侘|わ}びてます",
        "{汚|よご}れてしまう{前|まえ}に{大事|だいじ}に{壊|こわ}せますか？",
        "{変|か}わらないものだけを{今|いま}は{数|かぞ}えている",
        "{何時|いつ}もあなたに{伝|つた}えたくても",
        "{言葉|ことば}に{出来|でき}ない{私|わたし}です",
        "きっとそれは{幸|しあわ}せの{悪戯|いたずら}で",
        "{今日|きょう}もありがとうがシャイな{様|よう}です",
        "キリが{無|な}い{迷|まよ}い{達|たち}と ポピュラーミュージック {僕|ぼく}らの{真実|しんじつ}を{抱|だ}いて",
        "{枯|か}れない{何|なに}かをこの{先|さき}も{探|さが}していたい",
        "{抱|だ}きしめすぎる{前|まえ}に{僕|ぼく}は{何時|いつ}か{気付|きづ}けますか？",
        "{変|か}われないところだけを{今|いま}は{数|かぞ}えてしまう",
        "{何時|いつ}もは{痛|いた}い{胸|むね}らへんが",
        "{今日|きょう}はなんだか{高鳴|たかな}ってる",
        "{休|やす}みは{何|なに}しようかな {映|えい}{画|が}でも{観|み}ようかな",
        "そんな{調子|ちょうし}で{生|い}きろエヴリデイ",
        "{人間|にんげん}の{数|かず}だけ すれ{違|ちが}いが{起|お}きていて",
        "{偶|たま}に{嫌|いや}になる",
        "{綺麗|きれい}なままで{擦|す}れることなく{自由|じゆう}でいて",
        "そうすればきっと {巡|めぐ}りあえる",
        "{ロマンス|ろまんす}の{香|かお}りに{誘|さそ}われて{出会|であ}って",
        "{恋|こい}をまた{知|し}って {愛|あい}に{怒|おこ}られて",
        "{優|やさ}しさを{食|た}べて {田|たんぼ}{道|みち}も{走|はし}って",
        "{未|いま}だ{見|み}ぬ{思|おも}い{出|で} {期待|きたい}だけはさせてね",
        "{何時|いつ}もあなたに{伝|つた}えたくても",
        "{言葉|ことば}に{出来|でき}ない{私|わたし}です",
        "きっとそれは{幸|しあわ}せの{悪戯|いたずら}で",
        "{今日|きょう}もありがとうがシャイな{様|よう}です",
        "{私|わたし}{色|いろ}で{彩|いろど}って",
        "{誰|だれ}とも{比|くら}べないスタンスで",
        "{何時|あるひ}か{突|とつ}{然|ぜん}{花|はな}が{咲|さ}いたらラッキー",
        "そんな{調子|ちょうし}で{生|い}きろエヴリデイ",
        "{明日|あした}を{超|こ}えていかなきゃいけない（{言|い}えない {上手|うま}くは{言|い}えない だからこそ）",
        "{笑|わら}っていたいよね",
        "{手|て}を{取|と}ってる{実感|じっかん}が{欲|ほ}しい (You & I, you & I, you & I あなたもね)",
        "{皆|みんな}そうよね"
      ],
      "chinese": [
        "無盡地響個不停",
        "無論酸甜苦辣、抓痕都愛著",
        "現在也在等待著什麼缺少的東西",
        "在弄髒之前，能珍重地摧毀它嗎？",
        "現在只數著那些不變的東西",
        "總是想傳達給你",
        "我卻無法用言語表達",
        "那一定是幸福的惡作劇",
        "今天也因害羞無法說出「謝謝」",
        "無止盡的迷茫與流行音樂，抱著我們的真實",
        "也想在未來繼續尋找那不會枯萎的東西",
        "在抱得過緊之前，我能有所察覺嗎？",
        "現在卻只數著那些無法改變的地方",
        "總是疼痛的胸口",
        "今天卻莫名地悸動著",
        "假日做些什麼好呢？ 看部電影吧？",
        "這樣的調調過每一天吧",
        "人有多少，就有多少錯過",
        "有時會厭煩",
        "保持純潔，不受磨損，保持自由",
        "這樣一定能再度相遇",
        "被浪漫的香氣吸引而邂逅",
        "再次了解戀愛，為愛而生氣",
        "品嚐溫柔，奔跑在稻田小徑上",
        "尚未見到的回憶，請讓我充滿期待吧",
        "總是想傳達給你",
        "我卻無法用言語表達",
        "那一定是幸福的惡作劇",
        "今天也因害羞無法說出「謝謝」",
        "用我的色彩渲染",
        "不與任何人比較的立場",
        "某天突然開花的話，那就幸運了",
        "這樣的調調過每一天吧",
        "必須超越明日（說不出 不能流暢地說 因此更要）",
        "希望能微笑吧",
        "想要握著手的真實感 (You & I, you & I, you & I，你也是吧)",
        "大家都是這樣的吧"
      ]
    }
    
  },
  {
    "id": 10,
    "title": "正解",
    "artist": "RADWIMPS",
    "album": "正解",
    "release": "2024/2/28",
    "img": "./images/10.jpg",
    "popularity": 11012,
    "lyrics":{
      "japanese": [
        "この{先|さき}に{出会|であ}うどんな{友|とも}とも",
        "{分|わ}かち{合|あ}えない{秘密|ひみつ}を{共|とも}にした",
        "それなのにたったひ{言|こと}の",
        "「ごめんね」だけ やけに{遠|とお}くて{言|い}えなかったり",
        "{明日|あした}も{会|あ}うのになぜか{僕|ぼく}らは",
        "{眠|ねむ}い{眼|め}こすり {夜通|よどお}しバカ{話|ばなし}",
        "{明|あ}くる{日|ひ} {案|あん}の{定|じょう} {机|つくえ}{並|なら}べて",
        "{居眠|いねむ}りして{怒|おこ}られてるのに{笑|わら}えてきて",
        "{理屈|りくつ}に{合|あ}わないことをどれだけやれるかが{青春|せいしゅん}だとでも",
        "{何処|どこ}かで{僕|ぼく}ら{思|おも}っていたのかな",
        "あぁ {答|こた}えがある{問|と}いばかりを",
        "{教|おそ}わってきたよ そのせいだろうか",
        "{僕|ぼく}たちが{知|し}りたかったのは",
        "{何時|いつ}も{正解|せいかい}など{未|まだ}{銀河|ぎんが}にもない",
        "{一番|いちばん}{大切|たいせつ}な{君|きみ}と {仲直|なかなお}りの{仕方|しかた}",
        "{大好|だいす}きなあの{子|こ}の {心|こころ}の{振向|ふりむ}かせ{方|かた}",
        "{何|なに}ひとつ{見|み}えない {僕|ぼく}らの{未来|みらい}だから",
        "{答|こた}えがすでにある {問|と}いなんかに",
        "{用|よう}などはない",
        "これまで{出会|であ}ったどんな{友|とも}とも",
        "{違|ちが}う{君|きみ}に{見|み}つけてもらった",
        "{自分|じぶん}をはじめて{好|す}きになれたの",
        "{分|わ}かるはずない {君|きみ}に{分|わ}かるはずもないでしょう",
        "{並|なら}んで{歩|ある}けど {何処|どこ}かで{追|お}い{続|つづ}けていた {君|きみ}の{背中|せなか}",
        "{明日|あした}からは もうそこにはない (もうそこにはない)",
        "あぁ {答|こた}えがある{問|と}いばかりを",
        "{教|おそ}わってきたよ そのせいだろうか",
        "{僕|ぼく}たちが{知|し}りたかったのは",
        "{何時|いつ}も{正解|せいかい}など{大人|おとな}も{知|し}らない",
        "{喜|よろこ}びが{溢|あふ}れて{止|と}まらない {夜|よる}の{眠|ねむ}り{方|かた}",
        "{悔|くや}しさで{滲|にじ}んだ {心|こころ}の{傷|きず}の{治|なお}し{方|かた}",
        "{傷|きず}ついた{友|とも}の {励|はげ}まし{方|かた}",
        "{貴方|あなた}とはじめて{怒鳴|どな}り{合|あ}った{日|ひ}",
        "{後|あと}で{聞|き}いたよ {君|きみ}は{笑|わら}っていたと",
        "{想|おも}いの{伝|つた}え{方|かた}がわからない",
        "{僕|ぼく}の{心|こころ} {君|きみ}は{無理矢理|むりやり}こじ{開|あ}けたの",
        "あぁ {答|こた}えがある{問|と}いばかりを",
        "{教|おそ}わってきたよ だけど{明日|あした}からは",
        "{僕|ぼく}だけの{正解|せいかい}をいざ {探|さが}しにゆくんだ",
        "また{会|あ}う{日|ひ}まで",
        "{次|つぎ}の{空欄|くうらん}に{当|あ}てはまる{言葉|ことば}を",
        "{書|か}き{入|い}れなさい ここでの{最後|さいご}の{問|と}い",
        "「{君|きみ}のいない {明日|あした}からの{日々|ひび}を",
        "{僕|ぼく}は({私|わたし}) {何時|きっと} {何時|きっと}」",
        "{制限|せいげん}{時間|じかん}は {貴方|あなた}のこれからの{人生|じんせい}",
        "{解答|かいとう}{用紙|ようし}は {貴方|あなた}のこれからの{人生|じんせい}",
        "{答|こた}え{合|あ}わせの {時|とき}に{私|わたし}はもういない",
        "だから {採点|さいてん}{基準|きじゅん}は {貴方|あなた}のこれからの{人生|じんせい}",
        "「よーい はじめ」"
      ],
      "chinese": [
        "在未來遇見的任何朋友",
        "一起分享著無法言說的秘密",
        "即便如此，只有一句「對不起」",
        "卻顯得遙遠，說不出口",
        "明天還會見面，但我們卻",
        "揉著瞌睡的眼睛，通宵講著無聊的話",
        "隔天 果不其然 坐在並排的桌前",
        "即使打瞌睡被罵，也覺得好笑",
        "能做多少不合理的事就是青春",
        "不知為何，我們可能這麼認為",
        "啊，都是有答案的問題",
        "我一直被教導 這就是原因吧",
        "我們真正想知道的是",
        "總是那些銀河中也尚未有的正解",
        "最重要的是和你和好的方法",
        "讓喜歡的那個人回心轉意的方法",
        "因為我們看不見任何未來",
        "所以已經有答案的問題",
        "一點用處也沒有",
        "直到現在遇到的任何朋友",
        "都不同於由你發現的我",
        "第一次讓自己喜歡上自己",
        "你不可能知道 你不可能明白吧",
        "雖然並肩而行，但在某處總是在追隨著你的背影",
        "從明天起，已經不再有那背影",
        "啊，都是有答案的問題",
        "我一直被教導 這就是原因吧",
        "我們真正想知道的是",
        "總是那些大人也不知道的正解",
        "無法抑制的喜悅，夜晚的入睡方式",
        "為悔恨滲透的心傷的治癒方法",
        "安慰受傷朋友的方式",
        "第一次與你吵架的那天",
        "後來聽說你在笑",
        "不知道該如何傳達思念",
        "我的心 被你硬是撬開",
        "啊，都是有答案的問題",
        "我一直被教導 但是從明天起",
        "我要去尋找屬於我自己的正解",
        "直到再會的那一天",
        "請在下一個空格中填入合適的詞語",
        "這是最後的問題",
        "「沒有你的日子，從明天起",
        "我（我）一定 一定」",
        "限時是 你未來的人生",
        "答案紙是 你未來的人生",
        "對答案時我已經不在",
        "因此，評分標準是 你未來的人生",
        "「預備 開始」"
      ]
    }    
  },
  {
    "id": 11,
    "title": "うるうびと",
    "artist": "RADWIMPS",
    "album": "余命10年 ～Original Soundtrack～",
    "release": "2022/3/4",
    "img": "./images/11.jpg",
    "popularity": 40417,
    "lyrics":{
      "japanese": [
        "ホントみたいな{嘘|うそ}ばかり {頬張|ほおば}り{続|つづ}ける{世界|せかい}で",
        "{嘘|うそ}みたいなホントばかり {抱|かか}えた{君|きみ}は{窮屈|きゅうくつ}そうに {笑|わら}った",
        "{元気|げんき}すぎるこの{身体|からだ}に {飽|あ}きた{頃|ころ}に{熱|ねつ}が{出|で}ると",
        "{何故|なぜ}か{妙|みょう}に{嬉|うれ}しくてさ {大|おお}きな{声|こえ}で {母|はは}の{元|もと}へと{駆|か}けた",
        "{心|こころ}の{色|いろ} {形|かたち} まるで{違|ちが}う",
        "{二|ふた}つの{魂|たましい}が{混|ま}ざった{時|とき} {何|なに}が{起|お}こるかな",
        "{何時|あと}いくつ{心臓|しんぞう}があれば{僕|ぼく}は{君|きみ}の{手|て}を{掴|つか}んで",
        "この{胸|むね}の{中|なか}に {攫|さら}えるだろう",
        "{今|いま}や{人類|じんるい}はこの{地球|ちきゅう}を {飛|と}び{出|だ}し{火星|かせい}を{目指|めざ}す",
        "なのに{僕|ぼく}は20センチ{先|さき}の {君|きみ}の{方|ほう}が{遠|とお}い",
        "{小|ちい}さすぎるその{背中|せなか}に {大|おお}きすぎる{運命|うんめい}{背負|せお}い",
        "「{僕|ぼく}も{持|も}つよ」と{手|て}{貸|か}そうにも この{手|て}すり{抜|ぬ}け {主|ぬし}の{元|もと}へと{帰|かえ}る",
        "{目|め}を{離|はな}したらすぐにまた",
        "{鼾|いびき}を{掻|か}きはじめる{僕|ぼく}の {細胞|さいぼう}{起|お}こしたのは",
        "{何時|あと}いくつ{心臓|しんぞう}があれば {君|きみ}にこの{気持|きも}ちを",
        "{過不足|かふそく}なく{僕|ぼく}は {伝|つた}えられるのだろう",
        "{今|いま}や{人類|じんるい}を{超|こ}える{知能|ちのう}が {生|う}まれているのに",
        "{僕|ぼく}の{言葉|ことば}は{足踏|あしぶ}みを ただ{繰|く}り{返|かえ}す",
        "{全人類|ぜんじんるい}から10{分|ふん}ずつだけ{寿命|じゅみょう}をもらい",
        "{君|きみ}の{中|なか}{何|どう}にか {埋|う}め{込|こ}めやしないのかい",
        "それか{僕|ぼく}の{残|のこ}りの {命|いのち}を{二等分|にとうぶん}して",
        "{片方|かたっぽ}をあなたに {渡|わた}せやしないのかい",
        "そしたら「せーの」で",
        "{来世|らいせ}に {乗|の}れる",
        "{何時|あと}いくつ{心臓|しんぞう}があれば{僕|ぼく}は{君|きみ}の{手|て}を{掴|つか}んで",
        "この{胸|むね}の{中|なか}に {攫|さら}えるだろう",
        "{今|いま}や{人類|じんるい}はこの{地球|ちきゅう}を {飛|と}び{出|だ}し{火星|かせい}を{目指|めざ}す",
        "だけど{僕|ぼく}は20センチ{先|さき}の {君|きみ}だけを{目指|めざ}す",
        "この{一|ひと}つの{心臓|しんぞう}が{声|こえ}の{限|かぎ}りに{叫|さけ}ぶよ",
        "「あなたは{私|わたし}がこの{世界|せかい}に {生|い}きた{意味|いみ}でした」"
      ],
      "chinese": [
        "在滿是像真的一樣的謊言的世界中",
        "擁抱著像謊言一樣的真實，你似乎有些窒息地微笑",
        "當厭倦了過於健康的身體後發燒時",
        "不知為何感到格外開心，大聲地跑向母親",
        "心的顏色、形狀完全不同",
        "當兩個靈魂混合時會發生什麼呢",
        "還需要多少顆心臟才能抓住你的手",
        "將你帶進我的胸膛",
        "如今人類已經離開地球，目標是火星",
        "然而20公分外的你卻比火星還遙遠",
        "小小的背影承載著過於沉重的命運",
        "即使想說「我也能承擔」，手卻穿透了，回到主人的身旁",
        "一不注意就馬上再次",
        "開始打鼾，是你喚醒了我的細胞",
        "還需要多少顆心臟才能",
        "毫無偏差地傳達這份心意",
        "即便人類已誕生出超越的智慧",
        "我的言語卻只能原地踏步，反覆重複",
        "從全人類各取10分鐘的壽命",
        "是否無法將它植入你的體內呢",
        "或者將我剩下的生命對半分",
        "把一半交給你，是否可以呢",
        "然後一起「預備—走！」",
        "轉世同行",
        "還需要多少顆心臟才能抓住你的手",
        "將你帶進我的胸膛",
        "如今人類已經離開地球，目標是火星",
        "但我只將20公分外的你當作目標",
        "這顆心臟用盡聲音叫喊",
        "「你是我活在這個世界上的意義」"
      ]
    }    
  },
  {
    "id": 12,
    "title": "祝祭 feat.三浦透子",
    "artist": "RADWIMPS",
    "album": "天気の子 complete version",
    "release": "2019/11/27",
    "img": "./images/12.jpg",
    "popularity": 45226,
    "lyrics":{
      "japanese": [
        "{聴|き}きたい{曲|きょく}も{見|み}つからない {憂鬱|ゆううつ}な{一日|いちにち}の{始|はじ}まりが",
        "{君|きみ}の{大袈裟|おおげさ}な「おはよう」で {全|すべ}て{変|か}わってしまう{不思議|ふしぎ}",
        "{君|きみ}の{言葉|ことば}はなぜだろう {全|すべ}て{映画|えいが}で{言|い}うところの",
        "クライマックスの{決|き}め{台詞|せりふ}のように{大袈裟|おおげさ}で{好|す}き",
        "{臆病|おくびょう}とは{病|やまい}だとしたら {治|なお}る{気配|けはい}もない{僕|ぼく}の",
        "{目|め}の{前|まえ}に{現|あらわ}れたあなたは まるでさも{救世主|きゅうせいしゅ}の{顔|かお}",
        "{僕|ぼく}の{中|なか}を{光|ひか}らせる{鍵|かぎ}を なぜに{君|きみ}に{持|も}たせたのか",
        "その{訳|わけ}をただ{知|し}るそのために {生|い}きてみるのも{悪|わる}くはないよね",
        "{君|きみ}じゃないとないよ {意味|いみ}はひとつもないよ",
        "ムキになって「なんでよ?」って{聞|き}かないでよ",
        "キリがないが{言|い}うよ {君|きみ}がいい{理由|りゆう}を",
        "2020{番目|ばんめ}からじゃあ{言|い}うよ",
        "キリがないが{言|い}うよ {君|きみ}がいい{理由|りゆう}を",
        "1{番目|ばんめ}は{君|きみ}があてて"
      ],
      "chinese": [
        "找不到想聽的歌曲，鬱悶的一天開始了",
        "因為你誇張的「早安」，一切都改變了，真是不可思議",
        "為什麼你的話語總像電影中的",
        "高潮台詞般誇張，卻讓我喜歡",
        "如果說膽小是一種病，那麼完全沒有治癒的跡象",
        "出現在我面前的你，真像救世主的模樣",
        "為什麼把點亮我內心的鑰匙交給了你",
        "為了知道那個原因，活著似乎也不錯",
        "若不是你，一點意義都沒有",
        "不要認真地問「為什麼啊？」",
        "雖然說不盡，但我會告訴你喜歡你的理由",
        "從第2020個開始說吧",
        "雖然說不盡，但我會告訴你喜歡你的理由",
        "第一個理由就請你來猜猜看"
      ]
    }    
  },
  {
    "id": 13,
    "title": "愛にできることはまだあるかい",
    "artist": "RADWIMPS",
    "album": "天気の子 complete version",
    "release": "2019/11/27",
    "img": "./images/13.jpg",
    "popularity": 48450,
    "lyrics":{
      "japanese": [
        "{愛|あい}にできることは{未|まだ}あるかい",
        "{何|なに}も{持|も}たずに{生|う}まれ{落|お}ちた{僕|ぼく}",
        "{永遠|えいえん}の{隙間|すきま}でのたうち{回|まわ}ってる",
        "{諦|あきら}めたものと{賢|かしこ}いものだけが",
        "{勝者|しょうしゃ}の{時代|じだい}に{何処|どこ}で{息|いき}を{吸|す}う",
        "{支配者|しはいしゃ}も{神|かみ}も{何処|どこ}か{他人顔|たにんがお}",
        "だけど{本当|ほんとう}は{分|わ}かってるはず",
        "{勇気|ゆうき}や{希望|きぼう}や{絆|きずな}とかの{魔法|まほう}",
        "{使|つか}い{道|みち}もなく{大人|おとな}は{目|め}を{背|そむ}ける",
        "それでもあの{日|ひ}の{君|きみ}が{今|いま}も{未|まだ}",
        "{僕|ぼく}の{全|ぜん}{正義|せいぎ}のど{真|ま}ん{中|なか}にいる",
        "{世界|せかい}が{背中|せなか}を{向|む}けても{未|まだ}なお",
        "{立|た}ち{向|む}かう{君|きみ}が{今|いま}もここにいる",
        "{愛|あい}にできることは{未|まだ}あるかい",
        "{僕|ぼく}にできることは{未|まだ}あるかい",
        "{君|きみ}がくれた{勇気|ゆうき}だから",
        "{君|きみ}のために{使|つか}いたいんだ",
        "{君|きみ}と{分|わ}け{合|あ}った{愛|あい}だから",
        "{君|きみ}とじゃなきゃ{意味|いみ}がないんだ",
        "{愛|あい}にできることは{未|まだ}あるかい",
        "{僕|ぼく}にできることは{未|まだ}あるかい",
        "{定|さだ}めとはつまりサイコロの{出|で}た{目|め}",
        "はたまた{神|かみ}のいつものきまぐれ",
        "{選|えら}び{選|えら}ばれた {脱|ぬ}げられぬ{鎧|よろい}",
        "もしくは{遥|はる}かな{揺|ゆ}らぐことない{意志|いし}",
        "{果|は}たさぬ{願|ねが}いと {叶|かな}わぬ{再会|さいかい}と",
        "{解|と}けぬ{誤解|ごかい}と {降|ふ}り{積|つ}もる{憎悪|ぞうお}と",
        "{許|ゆる}し{合|あ}う{声|こえ}と {握|にぎ}りしめ{合|あ}う{手|て}を",
        "この{星|ほし}は{今日|きょう}も {抱|かか}えて{生|い}きてる",
        "{愛|あい}にできることは{未|まだ}あるかい",
        "{僕|ぼく}にできることは{未|まだ}あるかい",
        "{君|きみ}がくれた{勇気|ゆうき}だから",
        "{君|きみ}のために{使|つか}いたいんだ",
        "{君|きみ}と{育|そだ}てた{愛|あい}だから",
        "{君|きみ}とじゃなきゃ{意味|いみ}がないんだ",
        "{愛|あい}にできることは{未|まだ}あるかい",
        "{僕|ぼく}にできることは{未|まだ}あるかい",
        "{何|なに}もない{僕|ぼく}たちになぜ{夢|ゆめ}を{見|み}させたか",
        "{終|お}わりある{人生|じんせい}になぜ{希望|きぼう}を{持|も}たせたか",
        "なぜこの{手|て}をすり{抜|ぬ}けるものばかり{与|あた}えたか",
        "それでもなおしがみつく{僕|ぼく}らは{醜|みにく}いかい",
        "それとも{綺麗|きれい}かい",
        "{答|こた}えてよ",
        "{愛|あい}の{歌|うた}も{歌|うた}われ{尽|つ}くした",
        "{数多|あまた}の{映画|えいが}で{語|かた}られ{尽|つ}くした",
        "そんな{荒野|こうや}に{生|う}まれ{落|お}ちた{僕|ぼく}、{君|きみ}",
        "それでも",
        "{愛|あい}にできることは{未|まだ}あるよ",
        "{僕|ぼく}にできることは{未|まだ}あるよ"
      ],
      "chinese": [
        "愛能做到的事還有嗎？",
        "赤裸裸地降生的我",
        "在永恆的縫隙中翻滾著",
        "只有放棄和聰明的人",
        "在這個勝者的時代中如何呼吸",
        "支配者和神明一副事不關己的樣子",
        "但其實心裡明白",
        "勇氣、希望、羈絆這樣的魔法",
        "沒有使用方法，大人們選擇視而不見",
        "即使如此，那天的你依然",
        "在我所有正義的正中央",
        "即使全世界都背向而去",
        "依然在此直面一切的你",
        "愛能做到的事還有嗎？",
        "我能做到的事還有嗎？",
        "因為是你給予的勇氣",
        "我想為了你而使用",
        "因為是與你分享的愛",
        "如果不是和你就沒有意義",
        "愛能做到的事還有嗎？",
        "我能做到的事還有嗎？",
        "所謂的命運，不過是骰子的結果",
        "或許是神一如既往的隨性",
        "選擇與被選擇的，無法脫下的盔甲",
        "抑或是遙遠且堅定的意志",
        "未實現的願望，未完成的重逢",
        "無法解開的誤解，層層堆積的仇恨",
        "互相原諒的聲音，緊握著的雙手",
        "這顆星球今日依然懷抱著它們活著",
        "愛能做到的事還有嗎？",
        "我能做到的事還有嗎？",
        "因為是你給予的勇氣",
        "我想為了你而使用",
        "因為是與你一起培育的愛",
        "如果不是和你就沒有意義",
        "愛能做到的事還有嗎？",
        "我能做到的事還有嗎？",
        "為什麼讓我們這些一無所有的人做夢",
        "為什麼讓我們在有限的人生中懷有希望",
        "為什麼給了我們這雙總是抓不住的手",
        "即使如此，還是緊緊不放的我們，是醜陋嗎？",
        "還是美麗呢？",
        "請回答我",
        "愛的歌已經被唱盡了",
        "無數電影裡也已被說盡了",
        "降生在這樣荒蕪的世界中的我和你",
        "即使如此",
        "愛能做到的事還有喔",
        "我能做到的事還有喔"
      ]
    }
  },
  {
    "id": 14,
    "title": "夢灯籠",
    "artist": "RADWIMPS",
    "album": "君の名は。",
    "release": "2019/11/27",
    "img": "./images/14.jpg",
    "popularity": 78923,
    "lyrics":{
      "japanese": [
        "あぁ このまま{僕|ぼく}たちの{声|こえ}が",
        "{世界|せかい}の{端|はし}っこまで{消|き}えることなく{届|とど}いたりしたらいいのにな",
        "そしたらねぇ {二人|ふたり}で どんな{言葉|ことば}を{放|はな}とう",
        "{消|き}えることない{約束|やくそく}を {二人|ふたり}で「せーの」で {言|い}おう",
        "あぁ「{願|ねが}ったらなにがしかが{叶|かな}う」",
        "その{言葉|ことば}の{眼|め}をもう{見|み}れなくなったのは",
        "{一体|いったい}{何時|いつ}からだろうか {何故|なにゆえ}だろうか",
        "あぁ {雨|あめ}の{止|や}むまさにその{切|き}れ{間|ま}と {虹|にじ}の{出発点|しゅっぱつてん} {終点|しゅうてん}と",
        "この{命|いのち}{果|は}てる{場所|ばしょ}に{何|なに}かがあるって",
        "{何時|いつ}も{言|い}い{張|は}っていた",
        "{何時|いつ}か{行|い}こう {全生命|ぜんせいめい}も{未到|みとう} {未開拓|みかいたく}の",
        "{感情|かんじょう}にハイタッチして {時間|じかん}にキスを",
        "５{次元|じげん}にからかわれて それでも{君|きみ}を{見|み}るよ",
        "また「はじめまして」の{合図|あいず}を {決|き}めよう",
        "{君|きみ}の{名|な}を {今|いま}{追|お}いかけるよ"
      ],
      "chinese": [
        "啊，就這樣讓我們的聲音",
        "傳遞到世界的盡頭而不消失就好了",
        "這樣的話，兩個人一起放出什麼樣的話語呢",
        "說出那永不消失的約定，兩人一起「預備，開始」",
        "啊，「願望若成真，必有成就」",
        "從什麼時候開始已經無法再看見這句話的真諦",
        "究竟是從什麼時候，為什麼呢",
        "啊，雨停的那瞬間，虹的起點與終點",
        "在這條生命終結的地方，是否有什麼存在",
        "我一直這樣堅信著",
        "總有一天前往，那所有生命未曾到達，未開拓的",
        "和情感擊掌，親吻時間",
        "被五次元戲弄著，即便如此我還是注視著你",
        "讓我們再次決定那「初次見面」的信號吧",
        "我現在正在追尋你的名字"
      ]
    }    
  },
  {
    "id": 15,
    "title": "前前前世(movie ver.)",
    "artist": "RADWIMPS",
    "album": "君の名は。",
    "release": "2019/11/27",
    "img": "./images/15.jpg",
    "popularity": 60642,
    "lyrics":{
      "japanese": [
        "やっと{眼|め}を{覚|さ}ましたかい それなのになぜ{眼|め}も{合|あ}わせやしないんだい？",
        "「{遅|おそ}いよ」と{怒|おこ}る{君|きみ} これでもやれるだけ{飛|と}ばしてきたんだよ",
        "{心|こころ}が{身体|からだ}を{追|お}い{越|こ}してきたんだよ",
        "{君|きみ}の{髪|かみ}や{瞳|ひとみ}だけで{胸|むね}が{痛|いた}いよ",
        "{同|おな}じ{時|とき}を{吸|す}いこんで{離|はな}したくないよ",
        "{遥|はる}か{昔|むかし}から{知|し}る その{声|こえ}に",
        "{生|う}まれてはじめて {何|なに}を{言|い}えばいい？",
        "{君|きみ}の{前前前世|ぜんぜんぜんせ}から{僕|ぼく}は {君|きみ}を{探|さが}しはじめたよ",
        "そのぶきっちょな{笑|わら}い{方|かた}をめがけて やってきたんだよ",
        "{君|きみ}が{全然|ぜんぜん}{全部|ぜんぶ}{無|な}くなって チリヂリになったって",
        "もう{迷|まよ}わない また１から{探|さが}しはじめるさ",
        "むしろ０から また{宇宙|うちゅう}をはじめてみようか",
        "{何処|どこ}から{話|はな}すかな {君|きみ}が{眠|ねむ}っていた{間|あいだ}のストーリー",
        "{何億|なんおく} {何光年|なんこうねん}{分|ぶん}の{物語|ものがたり}を{語|かた}りにきたんだよ けどいざその{姿|すがた}この{眼|め}に{映|うつ}すと",
        "{君|きみ}も{知|し}らぬ{君|きみ}とジャレて {戯|たわむ}れたいよ",
        "{君|きみ}の{消|き}えぬ{痛|いた}みまで{愛|あい}してみたいよ",
        "{銀河|ぎんが}{何個分|なんこぶん}かの {果|は}てに{出会|であ}えた",
        "その{手|て}を{壊|こわ}さずに {何|どう}{握|にぎ}ったならいい？",
        "{君|きみ}の{前前前世|ぜんぜんぜんせ}から{僕|ぼく}は {君|きみ}を{探|さが}しはじめたよ",
        "その{騒|さわ}がしい{声|こえ}と{涙|なみだ}をめがけ やってきたんだよ",
        "そんな{革命前夜|かくめいぜんや}の{僕|ぼく}らを{誰|だれ}が{止|と}めるというんだろう",
        "もう{迷|まよ}わない {君|きみ}のハートに{旗|はた}を{立|た}てるよ",
        "{君|きみ}は{僕|ぼく}から{諦|あきら}め{方|かた}を {奪|うば}い{取|と}ったの",
        "{前前前世|ぜんぜんぜんせ}から{僕|ぼく}は {君|きみ}を{探|さが}しはじめたよ",
        "そのぶきっちょな{笑|わら}い{方|かた}をめがけて やってきたんだよ",
        "{君|きみ}が{全然|ぜんぜん}{全部|ぜんぶ}{無|な}くなって チリヂリになったって",
        "もう{迷|まよ}わない また１から{探|さが}しはじめるさ",
        "{何光年|なんこうねん}でも この{歌|うた}を{口|くち}ずさみながら"
      ],
      "chinese": [
        "終於醒來了嗎，然而為什麼不和我對視呢？",
        "「太慢了」你生氣地說著，但我已經盡力加速趕來了",
        "我的心早已超越身體追來了",
        "只看著你的頭髮和眼瞳就讓我的胸口疼痛",
        "想要吸入同樣的時間，想要永不分離",
        "那自遙遠過去就認識的聲音",
        "生來第一次，我該說些什麼？",
        "從前前前世開始我就在尋找你",
        "就是為了那笨拙的笑容，才來到這裡",
        "即使你一切全都消失，變得支離破碎",
        "也不會再迷茫，我會從1開始重新尋找",
        "甚至從0開始，再次創造宇宙吧",
        "該從哪裡說起呢，關於你沉睡期間的故事",
        "帶著幾億幾光年的故事而來，然而一看到你的身影",
        "想要和那連你自己都不知道的你玩耍嬉戲",
        "甚至想要愛著你那無法抹去的痛苦",
        "在數個銀河彼端相遇",
        "握住那雙手卻不傷害它，該怎麼握住才好？",
        "從前前前世開始我就在尋找你",
        "就是為了那喧鬧的聲音與眼淚，才來到這裡",
        "誰能阻止我們革命前夜的我們",
        "我不會再迷茫，我會在你的心上插上旗幟",
        "你從我這裡奪走了放棄的方法",
        "從前前前世開始我就在尋找你",
        "就是為了那笨拙的笑容，才來到這裡",
        "即使你一切全都消失，變得支離破碎",
        "也不會再迷茫，我會從1開始重新尋找",
        "不論幾光年，我都會哼著這首歌前進"
      ]
    }    
  },
  {
    "id": 16,
    "title": "スパークル(movie ver.)",
    "artist": "RADWIMPS",
    "album": "君の名は。",
    "release": "2019/11/27",
    "img": "./images/16.jpg",
    "popularity": 56813,
    "lyrics":{
      "japanese": [
        "{未|まだ}この{世界|せかい}は{僕|ぼく}を{飼|か}いならしてたいみたいだ",
        "{望|のぞ}み{通|どお}りいいだろう",
        "{美|うつく}しくもがくよ",
        "{互|たが}いの{砂時計|すなどけい}",
        "{眺|なが}めながらキスをしようよ",
        "「さよなら」から{一番|いちばん} {遠|とお}い{場所|ばしょ}で{待|ま}ち{合|あ}わせよう",
        "ついに{時|とき}はきた",
        "{昨日|きのう}までは{序章|じょしょう}の{序章|じょしょう}で",
        "{飛|と}ばし{読|よ}みでいいから",
        "ここからが{僕|ぼく}だよ",
        "{経験|けいけん}と{知識|ちしき}と",
        "カビの{生|は}えかかった{勇気|ゆうき}を{持|も}って",
        "{未|いま}だかつてないスピードで",
        "{君|きみ}のもとへダイブを",
        "{微睡|まどろ}みの{中|なか}で{生温|なまあたた}いコーラに",
        "ここでないどこかを{夢見|ゆめみ}たよ",
        "{教室|きょうしつ}の{窓|まど}の{外|そと}に",
        "{電車|でんしゃ}に{揺|ゆ}られ{運|はこ}ばれる{朝|あさ}に あぁ",
        "{運命|うんめい}だとか{未来|みらい}とかって",
        "{言葉|ことば}がどれだけ{手|て}を",
        "{伸|の}ばそうと{届|とど}かない",
        "{場所|ばしょ}で{僕|ぼく}ら{恋|こい}をする",
        "{時計|とけい}の{針|はり}も{二人|ふたり}を",
        "{横目|よこめ}に{見|み}ながら{進|すす}む",
        "こんな{世界|せかい}を{二人|ふたり}で",
        "{一生|いっしょう} いや {何章|なんしょう}でも",
        "{生|い}き{抜|ぬ}いていこう",
        "「{初|はじ}めまして」なんてさ",
        "{遥|はる}か{彼方|かなた}へと{追|お}いやって",
        "{千年周期|せんねんしゅうき}を {一日|いちにち}で{息|いき}しよう",
        "{辞書|じしょ}にある{言葉|ことば}で",
        "{出来上|できあ}がった{世界|せかい}を{憎|にく}んだ",
        "{万華鏡|まんげきょう}の{中|なか}で {八月|はちがつ}のある{朝|あさ}",
        "{君|きみ}は{僕|ぼく}の{前|まえ}で",
        "ハニかんでは{澄|す}ましてみせた",
        "この{世界|せかい}の{教科書|きょうかしょ}のような{笑顔|えがお}で",
        "{嘘|うそ}みたいな{日々|ひび}を {規格外|きかくがい}の{意味|いみ}を",
        "{悲劇|ひげき}だっていいから {望|のぞ}んだよ",
        "そしたらドアの{外|そと}に",
        "{君|きみ}が{全部|ぜんぶ}{抱|かか}えて {立|た}ってたよ あぁ",
        "{運命|うんめい}だとか{未来|みらい}とかって",
        "{言葉|ことば}がどれだけ{手|て}を",
        "{伸|の}ばそうと{届|とど}かない",
        "{場所|ばしょ}で{僕|ぼく}ら{遊|あそ}ぼうか",
        "{愛|あい}し{方|かた}さえも {君|きみ}の{匂|にお}いがした",
        "{歩|ある}き{方|かた}さえも その{笑|わら}い{声|ごえ}がした",
        "{何時|いつ}か{消|き}えてなくなる {君|きみ}のすべてを",
        "この{眼|め}に{焼|や}き{付|つ}けておくことは",
        "{何|もう}{権利|けんり}なんかじゃない {義務|ぎむ}だと{思|おも}うんだ",
        "{運命|うんめい}だとか{未来|みらい}とかって",
        "{言葉|ことば}がどれだけ{手|て}を",
        "{伸|の}ばそうと{届|とど}かない",
        "{場所|ばしょ}で{僕|ぼく}ら{恋|こい}をする",
        "{時計|とけい}の{針|はり}も{二人|ふたり}を",
        "{横目|よこめ}に{見|み}ながら{進|すす}む",
        "そんな{世界|せかい}を{二人|ふたり}で",
        "{一生|いっしょう} いや {何章|なんしょう}でも",
        "{生|い}き{抜|ぬ}いていこう"
      ],
      "chinese": [
        "啊，這個世界似乎還想馴服我",
        "如你所願，也好",
        "我會優雅地掙扎著",
        "互相凝視著沙漏",
        "邊親吻邊度過時光吧",
        "讓我們約在距離「再見」最遙遠的地方見面",
        "終於時刻到來了",
        "直到昨天為止只是序章的序章",
        "即使是快讀也無妨",
        "從這裡開始才是真正的我",
        "帶著經驗和知識",
        "以及發霉的勇氣",
        "以史無前例的速度",
        "向你跳躍而去",
        "在朦朧之中，啜飲著微溫的可樂",
        "夢想著某個不在此地的地方",
        "教室窗外",
        "在晨間隨電車搖晃運行的途中 啊",
        "無論命運或未來",
        "那些詞語無論如何伸手",
        "都無法觸及",
        "在那裡我們相戀",
        "時鐘的指針看著我們",
        "一邊瞟著一邊前進",
        "在這樣的世界中",
        "我們將一生，不，多少章節",
        "都一起走下去",
        "「初次見面」之類的",
        "丟到遙遠的彼方去吧",
        "以千年週期在一天中呼吸",
        "以字典中現存的詞彙",
        "構築的世界我憎恨",
        "在萬花筒中，某個八月的早晨",
        "你在我面前",
        "靦腆地展示著純淨的模樣",
        "如這世界教科書般的笑容",
        "過著如謊言般的日子，不合規格的意義",
        "即使是悲劇也無所謂，只要是我所期望的",
        "然後在門外",
        "你抱著一切站立著 啊",
        "無論命運或未來",
        "那些詞語無論如何伸手",
        "都無法觸及",
        "要不要在那裡一起玩耍？",
        "連愛的方式都帶著你的氣息",
        "連走路的樣子都帶著你的笑聲",
        "總有一天會消失的你的全部",
        "將它刻入眼中",
        "已不再是權利，而是義務",
        "無論命運或未來",
        "那些詞語無論如何伸手",
        "都無法觸及",
        "在那裡我們相戀",
        "時鐘的指針看著我們",
        "一邊瞟著一邊前進",
        "在這樣的世界中",
        "我們將一生，不，多少章節",
        "都一起走下去"
      ]
    }
  },
  {
    "id": 17,
    "title": "君と羊と青",
    "artist": "RADWIMPS",
    "album": "絶体絶命",
    "release": "2011/3/9",
    "img": "./images/17.jpg",
    "popularity": 46103,
    "lyrics":{
      "japanese": [
        "{今|いま}がその{時|とき}だともう{気付|きづ}いてたんだ {光|ひか}り{方|かた}は{教|おそ}わらずとも{知|し}っていた",
        "{眼|め}の{前|まえ}の{現在|げんざい}がもうすでに {思|おも}い{出色|でいろ}していた",
        "{奇跡|きせき}は{起|お}こるもんじゃなくて{起|お}こすものだと {手当|てあ}たり{次第|しだい}{ボタン|ぼたん}があれば{連打|れんだ}した",
        "『{今|いま}』がすり{切|き}れるくらいに{生|い}きてたんだ {精一杯|せいいっぱい} {目一杯|めいっぱい}を",
        "{喜怒哀楽|きどあいらく}の{全方位|ぜんほうい}を {縦横無尽|じゅうおうむじん}に{駆|か}け{抜|ぬ}けた{日々|ひび}を",
        "{君|きみ}を{見|み}つけ{出|だ}した{時|とき}の{感情|かんじょう}が {今|いま}も{骨|ほね}の{髄|ずい}まで{動|うご}かしてんだ",
        "{眩|まぶ}しすぎて{閉|と}じた{瞳|ひとみ}の{残像|ざんぞう}が {今|いま}もそこで{明日|あした}に{手|て}を{振|ふ}ってんだ",
        "{世界|せかい}が{僕|ぼく}らを{置|お}き{去|さ}りにするから {負|ま}けじと{彼|かれ}らをなおざりにしてやった",
        "するとどうだ{寂|さび}しがったこの{世界|せかい}が {向|む}こうから{割|わ}り{込|こ}んできた",
        "{今日|きょう}の{僕|ぼく}を{賞味|しょうみ}できる{期限|きげん}は{今日|きょう} {眠|ねむ}らせて {腐|くさ}らせるくらいならばと",
        "{青|あお}いままでヘタもとらず{落|お}ちた{僕|ぼく}を {君|きみ}が{受|う}け{取|と}ったんだ",
        "{苦|にが}いけど {苦|くる}しくはないよと",
        "{君|きみ}は {酸|す}っぱいけども {悪|わる}くはないよと そう{言|い}った",
        "{起承転結|きしょうてんけつ}の『{転|てん}』だけを {欲張|よくば}って{頬張|ほおば}った{僕|ぼく}らの{日々|ひび}よ",
        "『{結|けつ}』することなどのない{日々|ひび}を",
        "{君|きみ}を{見|み}つけ{出|だ}した{時|とき}の{感情|かんじょう}が この{五臓|ごぞう}の{六腑|ろっぷ}を{動|うご}かしてんだ",
        "{眩|まぶ}しすぎて{閉|と}じた{瞳|ひとみ}の{残像|ざんぞう}が {向|む}かうべき{道|みち}のりを{指差|ゆびさ}してんだ",
        "リアルと{夢|ゆめ}と{永遠|えいえん}と{今|いま}と{幻想|げんそう}が {束|たば}になって{僕|ぼく}を{胴上|どうあ}げしてんだ",
        "あの{日|ひ}{僕|ぼく}らを{染|そ}め{上|あ}げた{群青|ぐんじょう}が {今|いま}もこの{皮膚|ひふ}の{下|した}を{覆|おお}ってんだ"
      ],
      "chinese": [
        "啊，我已經察覺到了，這正是時候",
        "即便未被教導如何閃耀，也早已知曉",
        "眼前的當下早已染上了回憶的顏色",
        "奇蹟不是發生，而是創造的",
        "碰到什麼按鈕就瘋狂連按",
        "活得如同磨耗著『現在』一樣，全力以赴",
        "在喜怒哀樂的各個方向，縱橫無盡地奔馳著的日子",
        "當找到你的那份感情，如今依然滲透到骨髓深處，推動著我",
        "因過於耀眼而閉上的雙眼的殘影，至今依然在那裡，向著明天揮手",
        "因為這個世界把我們拋下，所以我們也不理會它們",
        "然後呢，這寂寞的世界反而從那邊插了進來",
        "今天的我，保鮮期限僅限今天",
        "既然如此，與其讓它沉睡或腐爛",
        "倒不如保持青澀未去蒂而墜落，而你將我接住",
        "「苦澀卻不覺得痛苦」",
        "「酸澀卻也不壞」你如此說道",
        "以『起承轉結』中的『轉』為主題，大口吞食的我們的日子",
        "那永遠沒有結局的日子",
        "當找到你的那份感情，驅動著我的五臟六腑",
        "因過於耀眼而閉上的雙眼的殘影，指向了應該前進的道路",
        "現實、夢想、永恆、當下與幻想，結成一束把我高高拋起",
        "那一天染上我們的群青，如今依然覆蓋在我皮膚之下"
      ]
    }
  },
  {
    "id": 18,
    "title": "05410-(ん)",
    "artist": "RADWIMPS",
    "album": "RADWIMPS 4～おかずのごはん～",
    "release": "2006/12/6",
    "img": "./images/18.jpg",
    "popularity": 33897,
    "lyrics":{
      "japanese": [
        "Wake me up wake me up wake me up when you come back",
        "I'll be here I'll be waiting here for you",
        "I can be your best friend",
        "I can be your least friend",
        "I can be your boy friend",
        "but I don't wanna be your ex-friend",
        "Don't you know this guy who sang a song",
        "about the highest common factor and so",
        "It's kind of how this is, I'll tell you what it is",
        "about all your questions you have asked",
        "Wake me up wake me up wake me up when you come back",
        "I'll be here I'll be waiting here for you",
        "If the size of the sky makes you frighten then come back",
        "And then cry so that I might could hug you",
        "これで{五度目|ごどめ}の{別|わか}れ{話|ばなし}です",
        "でも{今回|こんかい}はどこか{違|ちが}うんです",
        "いつもの『{忍法|にんぽう}・{記憶喪失|きおくそうしつ}』も",
        "{何故|なぜ}か{今回|こんかい}は{効|き}かないんです",
        "「もういやだ」って{思|おも}っていたんなら",
        "それでも{僕|ぼく}はいいけど",
        "「さよなら」って{言|い}ったのは{君|きみ}なのに",
        "{何故|なんで}{泣|な}いたの?",
        "Wake me up wake me up wake me up when you come back",
        "If that answer is“no”, what should I do?",
        "Should I cry? Should I die? Or go crazy and then fly",
        "Better yet should I kiss myself ドンマイ",
        "Wake me up wake me up wake me up when you come back",
        "Pick me up pick me up pick me up when you come back",
        "Wake me up wake me up wake me up when you come back",
        "I'll be here I'll be waiting here for you",
        "Pick me up pick me up pick me up when you come back",
        "Until then I will save this song for you",
        "Now come back now come back now come back I'll take it back",
        "I'll be here I'll be here I'll be waiting here for you"
      ],
      "chinese": [
        "喚醒我 喚醒我 當你回來時喚醒我",
        "我會在這裡 等待著你",
        "我可以成為你的最好朋友",
        "也可以成為你唯一的朋友",
        "我可以當你的男朋友",
        "但我不想成為你曾經的朋友",
        "你不認識那個唱著",
        "關於最大公因數的家伙嗎",
        "這就是這樣的感覺，我會告訴你",
        "關於你所有的疑問",
        "喚醒我 喚醒我 當你回來時喚醒我",
        "我會在這裡 等待著你",
        "如果天空的廣大讓你害怕，那就回來吧",
        "然後哭吧，好讓我可以擁抱你",
        "這已經是第五次說分手了",
        "但這次總覺得有點不同",
        "往常的『忍法・失憶術』",
        "不知為何這次卻沒效果",
        "如果你覺得「夠了，不想要了」",
        "那我也無所謂",
        "明明說「再見」的是你",
        "為什麼你卻哭了呢？",
        "喚醒我 喚醒我 當你回來時喚醒我",
        "如果答案是“不”，那我該怎麼辦？",
        "我該哭嗎？該去死嗎？還是瘋狂地飛起來？",
        "或更好的是，親吻自己 不要緊",
        "喚醒我 喚醒我 當你回來時喚醒我",
        "接住我 接住我 當你回來時接住我",
        "喚醒我 喚醒我 當你回來時喚醒我",
        "我會在這裡 等待著你",
        "接住我 接住我 當你回來時接住我",
        "直到那時，我會為你保存這首歌",
        "現在回來吧 現在回來吧 現在回來吧 我會再次接受它",
        "我會在這裡 我會在這裡 等待著你"
      ]
    }    
  },
  {
    "id": 19,
    "title": "me me she",
    "artist": "RADWIMPS",
    "album": "RADWIMPS 4～おかずのごはん～",
    "release": "2006/12/6",
    "img": "./images/19.jpg",
    "popularity": 86681,
    "lyrics":{
      "japanese": [
        "{僕|ぼく}を{光|ひか}らせて{君|きみ}を{曇|くも}らせた",
        "この{恋|こい}に{僕|ぼく}らの{夢|ゆめ}をのせるのは{重荷|おもに}すぎたかな",
        "{君|きみ}の{嫌|きら}いになり{方|かた}を{僕|ぼく}は{忘|わす}れたよ",
        "{何処|どこ}を{探|さが}しても{見当|みあ}たらないんだよ",
        "{彼日|あのひ}どうせなら",
        "「さよなら」と{一緒|いっしょ}に{教|おし}えて{欲|ほ}しかったよ",
        "{彼|あの}{約束|やくそく}の{破|やぶ}り{方|かた}を {他|ほか}の{誰|だれ}かの{愛|あい}し{方|かた}を",
        "だけど{本当|ほんと}は{知|し}りたくないんだ",
        "{約束|やくそく}したよね 「100{歳|さい}までよろしくね」",
        "101{年目|ねんめ}がこんなに{早|はや}くくるとは{思|おも}わなかったよ",
        "こんなこと{言|い}って {本当|ほんと}にごめんね",
        "{頭|あたま}で{分|わ}かっても{心|こころ}がごねるの",
        "だけどそんな{僕|ぼく}",
        "{造|つく}ってくれたのは {救|すく}ってくれたのは",
        "きっとパパでも {多分|たぶん}ママでも",
        "{神様|かみさま}でもないと{思|おも}うんだよ",
        "{残|のこ}るはつまり ほらね{君|きみ}だった",
        "{僕|ぼく}が{例|たと}えば{他|ほか}の{人|ひと}と{結|むす}ばれたとして",
        "{二人|ふたり}の{間|あいだ}に{命|いのち}が{宿|やど}ったとして",
        "その{中|なか}にもきっと {君|きみ}の{遺伝子|いでんし}もそっと",
        "{紛|まぎ}れこんでいるだろう",
        "でも{君|きみ}がいないなら きっとつまらないから",
        "{暇|ひま}つぶしがてら2085{年|ねん}まで{待|ま}ってるよ",
        "{今|いま}まで{本当|ほんと}にありがとう",
        "{今|いま}まで{本当|ほんと}にごめんね",
        "{今度|こんど}は{僕|ぼく}が{待|ま}つ{番|ばん}だよ",
        "{君|きみ}が{生|い}きていようとなかろうと",
        "だってはじめて{笑|わら}って{言|い}えた{約束|やくそく}なんだもん",
        "「さよなら」と{一緒|いっしょ}に {僕|ぼく}からの{言葉|ことば}を",
        "「ありがとう」と{一緒|いっしょ}に 「ごめんね」を",
        "「{空|そら}が{綺麗|きれい}だね {人|ひと}は{悲|かな}しいね」",
        "また{見|み}え{透|す}いた{本当|ほんと}で{僕|ぼく}を{洗|あら}ってよ",
        "{次|つぎ}が{何時|もし}あれば",
        "{僕|ぼく}の{好|す}きな{君|きみ} その{君|きみ}が{好|す}きな{僕|ぼく}",
        "そうやって{何時|いつ}しか{僕|ぼく}は{僕|ぼく}を{大切|たいせつ}に{思|おも}えたよ",
        "この{恋|こい}に{僕|ぼく}が{名前|なまえ}をつけるならそれは「ありがとう」"
      ],
      "chinese": [
        "讓我發光，也讓你黯淡的",
        "這份愛或許太沉重了，無法承載我們的夢想",
        "我已經忘了如何討厭你",
        "無論怎麼找都找不到",
        "若那天可以的話",
        "希望能和「再見」一起教給我",
        "如何打破那個約定，如何愛上別人",
        "但其實我不想知道",
        "曾約定的吧 「請陪我到一百歲」",
        "沒想到第一百零一年來得這麼快",
        "說這樣的話，真的對不起",
        "雖然頭腦明白，心卻不服從",
        "但造就這樣的我",
        "拯救了我的人",
        "我想也許既不是爸爸，或許也不是媽媽",
        "也不是神明",
        "也就是剩下的就是你啊",
        "假如我和其他人結合",
        "即使有了新生命",
        "其中也一定會悄悄融入你的基因",
        "但如果沒有你，想來一定很無趣",
        "就當打發時間，我會等到2085年",
        "至今真的謝謝你",
        "至今真的對不起",
        "這次該輪到我等了",
        "不管你是否活著",
        "因為這是我第一次笑著說出的約定",
        "和「再見」一起，將我的話語",
        "和「謝謝」一起，還有「對不起」",
        "「天空真美，人真悲傷」",
        "用這看穿一切的真心再次洗滌我吧",
        "若還有下一次",
        "我喜歡的你，喜歡我的你",
        "就這樣不知不覺中，我開始珍惜自己",
        "如果要給這份愛取名字，那就是「謝謝」"
      ]
    }    
  },
  {
    "id": 20,
    "title": "有心論",
    "artist": "RADWIMPS",
    "album": "RADWIMPS 4～おかずのごはん～",
    "release": "2006/12/6",
    "img": "./images/20.jpg",
    "popularity": 75725,
    "lyrics":{
      "japanese": [
        "{今|いま}まで{僕|ぼく}が{付|つ}いた{嘘|うそ}と",
        "{今|いま}まで{僕|ぼく}が{言|い}ったホント",
        "{何方|どっち}が{多|おお}いか{怪|あや}しくなって{探|さが}すのやめた",
        "{自分|じぶん}の{中|なか}の{嫌|きら}いなところ",
        "{自分|じぶん}の{中|なか}の{好|す}きなところ",
        "{何方|どっち}が{多|おお}いかもう{分|わ}かってて{悲|かな}しくなった",
        "{何時|どうせ}{何時|いつ}かは{嫌|きら}われるなら {愛|あい}した{人|ひと}に{憎|にく}まれるなら",
        "そうなる{前|まえ}に{僕|ぼく}の{方|ほう}から{嫌|きら}った{僕|ぼく}だった",
        "だけど{何時|いつ}かは{誰|だれ}かを{求|もと}め {愛|あい}されたいとそう{望|のぞ}むなら",
        "そうなる{前|まえ}に{僕|ぼく}の{方|ほう}から {愛|あい}してみてよと",
        "{君|きみ}があまりにも{綺麗|きれい}に{泣|な}くから {僕|ぼく}は{思|おも}わず{横|よこ}で{笑|わら}ったよ",
        "すると{君|きみ}もつられて{笑|わら}うから {僕|ぼく}は{嬉|うれ}しくて {泣|な}く {泣|な}く",
        "{明日|あした}を{呪|のろ}う{人間不信者|にんげんふしんしゃ}は {明日|あした}を{夢見|ゆめみ}る{人間信者|にんげんしんじゃ}に",
        "もう{昨日|きのう}を{探|さが}してた{僕|ぼく}はいない いない",
        "{君|きみ}は{人間|にんげん}{洗浄機|せんじょうき}",
        "この{機会|きかい}にどのご{家庭|かてい}に もひとつは{用意|ようい}して{頂|いただ}きたい",
        "こりゃ{買|か}わない{手|て}はない {嘘|うそ}ではない",
        "{驚|おどろ}くべき{効果|こうか}を{発揮|はっき}します",
        "{新|あたら}しい{自分|じぶん}に{出会|であ}えます",
        "ただ{中毒性|ちゅうどくせい}がごさいます",
        "{用法|ようほう}・{用量|ようりょう}をお{守|まも}りください",
        "こんなキャッチフレーズを{書|か}こう",
        "やっとこさ{君|きみ}のクローンが {成功|せいこう}した{時|とき}にでも",
        "だって{君|きみ}は{世界初|せかいはつ}の {肉眼|にくがん}で{確認|かくにん}できる{愛|あい}",
        "{地上|ちじょう}で{唯一|ゆいいつ}{出会|であ}える{神様|かみさま}",
        "{誰|だれ}も{隅|すみ}っこで{泣|な}かないようにと {君|きみ}は{地球|ちきゅう}を{丸|まる}くしたんだろう?",
        "だから{君|きみ}に{会|あ}えないと{僕|ぼく}は {隅|すみ}っこを{探|さが}して{泣|な}く {泣|な}く",
        "{誰|だれ}も{命|いのち}{無駄|むだ}にしないようにと {君|きみ}は{命|いのち}に{終|お}わり{作|つく}ったよ",
        "だから{君|きみ}がいないその{時|とき}は {僕|ぼく}は{息|いき}を{止|と}め {待|ま}つ",
        "するとね{君|きみ}は {何時|いつ}でもここに {来|き}てくれたのに",
        "もうここにいない いない",
        "{明日|あした}を{夢見|ゆめみ}た{人間信者|にんげんしんじゃ}は",
        "{明日|あした}の{死|し}を{待|ま}つ{自殺志願者|じさつしがんしゃ}に",
        "3{分前|ぷんまえ}の{僕|ぼく}がまた{顔|かお}を{出|だ}す",
        "{息|いき}を{止|と}めると{心|こころ}があったよ",
        "そこを{開|ひら}くと{君|きみ}がいたんだよ",
        "{左心房|さしんぼう}に{君|きみ}がいるなら{問題|もんだい}はない ない ないよね",
        "2{秒前|びょうまえ}までの{自殺志願者|じさつしがんしゃ}を",
        "{君|きみ}は{永久幸福論者|えいきゅうこうふくろんしゃ}に{変|か}えてくれた",
        "そんな{君|きみ}はもういない いない いない いないけど",
        "この{心臓|しんぞう}に{君|きみ}がいるんだよ",
        "{全身|ぜんしん}に{向|む}け{脈|みゃく}を{打|う}つんだよ",
        "{今日|きょう}も{生|い}きて {今日|きょう}も{生|い}きて",
        "そして{今|いま}のままでいてと",
        "{白血球|はっけっきゅう} {赤血球|せっけっきゅう} その他もろもろの{愛|あい}を{僕|ぼく}に{送|おく}る"
      ],
      "chinese": [
        "至今為止我撒的謊與",
        "至今為止我說的真話",
        "哪一個比較多已經難以辨別，放棄了去尋找",
        "自己討厭的部分",
        "自己喜歡的部分",
        "哪一個比較多已經明白了，變得悲傷",
        "反正總有一天會被討厭，如果會被所愛的人憎恨",
        "那在此之前，先由我主動討厭吧",
        "然而若總有一天我會渴求著某人，希望被愛",
        "那麼在此之前，請先由我主動去愛吧",
        "因為你哭得太美，我不禁在一旁笑了",
        "於是你也跟著笑了，我好開心，哭了，哭了",
        "詛咒明天的厭世者，成為憧憬明天的信仰者",
        "尋找昨日的我已經不再，不再",
        "你是人類清洗機",
        "我希望每個家庭都備上一台",
        "這真的很划算，這不是謊言",
        "效果令人驚奇",
        "能遇見全新的自己",
        "但有成癮性",
        "請遵守使用方法與劑量",
        "讓我寫下這樣的廣告詞",
        "當你的克隆人終於成功時",
        "因為你是世界上唯一用肉眼確認的愛",
        "是地上唯一可以相遇的神",
        "你讓地球變得圓滿，不讓任何人孤獨哭泣",
        "所以若我無法遇見你，我會在角落哭泣，哭泣",
        "你為了不讓任何生命白費，創造了生命的結束",
        "所以在你不在的時候，我會屏住呼吸等待",
        "於是你總是來到這裡",
        "但如今你已經不在，不在",
        "夢見明天的信仰者",
        "成為等待死亡的自殺志願者",
        "三分鐘前的我又浮現了",
        "屏住呼吸，感到心跳",
        "當我打開它，你在那裡",
        "若在左心房有你在，那就沒問題，沒問題，沒問題吧",
        "將兩秒前的自殺志願者",
        "變為永遠幸福的信仰者的你",
        "這樣的你已經不在，不在，不在，不在",
        "但這顆心臟裡有你",
        "將脈搏傳向全身",
        "今天也活著，今天也活著",
        "並且請保持如今的模樣",
        "白血球、紅血球，以及其他眾多的愛送給我"
      ]
    }    
  },
  {
    "id": 21,
    "title": "春泥棒",
    "artist": "ヨルシカ",
    "album": "創作(Type A)",
    "release": "2021/1/27",
    "img": "./images/21.jpg",
    "popularity": 89223,
    "lyrics":{
      "japanese": [
        "{高架橋|こうかきょう}を{抜|ぬ}けたら{雲|くも}の{隙間|すきま}に{青|あお}が{覗|のぞ}いた",
        "{最近|さいきん}{何時|どう}も{暑|あつ}いから ただ{風|かぜ}が{吹|ふ}くのを{待|ま}ってた",
        "{木陰|こかげ}に{座|すわ}る",
        "{何|なに}か{頬|ほお}に{付|つ}く",
        "{見上|みあ}げれば{頭上|ずじょう}に{咲|さ}いて{散|ち}る",
        "はらり {僕|ぼく}らもう{息|いき}も{忘|わす}れて",
        "{瞬|まばた}きさえ{億劫|おっくう}",
        "さぁ {今日|きょう}さえ{明日|あした}{過去|かこ}に{変|か}わる",
        "ただ{風|かぜ}を{待|ま}つ",
        "だから{僕|ぼく}らもう{声|こえ}も{忘|わす}れて",
        "さよならさえ{億劫|おっくう}",
        "ただ{花|はな}が{降|ふ}るだけ{晴|は}れり",
        "{今|いま} {春吹雪|はるふぶき}",
        "{次|つぎ}の{日|ひ}も{待|ま}ち{合|あ}わせ",
        "{花見|はなみ}の{客|きゃく}も{少|すく}なくなった",
        "{春|はる}の{匂|にお}いはもう{止|や}む",
        "{今年|ことし}も{夏|なつ}が{来|く}るのか",
        "{高架橋|こうかきょう}を{抜|ぬ}けたら{道|みち}の{先|さき}に{君|きみ}が{覗|のぞ}いた",
        "{残|のこ}りはどれだけかな",
        "どれだけ{春|はる}に{会|あ}えるだろう",
        "{川沿|かわぞ}いの{丘|おか} {木陰|こかげ}に{座|すわ}る",
        "また{昨日|きのう}と{変|か}わらず{今日|きょう}も{咲|さ}く{花|はな}に",
        "{僕|ぼく}らもう{息|いき}も{忘|わす}れて",
        "{瞬|まばた}きさえ{億劫|おっくう}",
        "{花散|はなち}らせ{今|いま}{吹|ふ}くこの{嵐|あらし}は",
        "まさに{春泥棒|はるどろぼう}",
        "{風|かぜ}に{今日|きょう}ももう{時|とき}が{流|なが}れて",
        "{立|た}つことさえ{億劫|おっくう}",
        "{花|はな}の{隙間|すきま}に{空|そら} {散|ち}れり",
        "{未|まだ} {春吹雪|はるふぶき}",
        "{今日|きょう}も{会|あ}いに{行|い}く",
        "{木陰|こかげ}に{座|すわ}る",
        "{溜息|ためいき}を{吐|は}く",
        "{花|はな}ももう{終|お}わる",
        "{明日|あした}も{会|あ}いに{行|い}く",
        "{春|はる}がもう{終|お}わる",
        "{名残|なご}るように{時間|じかん}が{散|ち}っていく",
        "{愛|あい}を{歌|うた}えば{言葉|ことば}{足|た}らず",
        "{踏|ふ}む{韻|いん}さえ{億劫|おっくう}",
        "{花開|はなひら}いた{今|いま}を{言葉|ことば}{如|ごと}きが{語|かた}れるものか",
        "はらり {僕|ぼく}らもう{声|こえ}も{忘|わす}れて",
        "{瞬|まばた}きさえ{億劫|おっくう}",
        "{花見|はなみ}は{僕|ぼく}らだけ",
        "{散|ち}るな{未|まだ} {春吹雪|はるふぶき}",
        "あともう{少|すこ}しだけ",
        "もう{数|かぞ}えられるだけ",
        "あと{花|はな}{二|ふた}つだけ",
        "もう{花|はな}{一|ひと}つだけ",
        "ただ{葉|は}が{残|のこ}るだけ はらり",
        "{今|いま} {春仕舞|はるじま}い"
      ],
      "chinese": [
        "穿過高架橋時從雲隙間透出的藍天",
        "最近天氣怎麼這麼熱，只能等待微風輕拂",
        "坐在樹蔭下",
        "感覺臉頰上有什麼",
        "抬頭一看，頭頂上的花正在盛開又飄落",
        "輕輕地，我們連呼吸都忘了",
        "甚至連眨眼都嫌麻煩",
        "今日終究會成為明日的過去",
        "只是靜靜等待微風",
        "所以我們連聲音也忘了",
        "連道別都嫌麻煩",
        "只是花瓣輕輕落下，晴朗無雲",
        "此刻，春日飄雪",
        "次日的約會",
        "來賞花的人也漸漸少了",
        "春天的氣息已經停止",
        "今年夏天也將來臨嗎",
        "穿過高架橋時在路的盡頭看到你",
        "還剩多少時光呢",
        "我們還能遇見多少次春天",
        "沿著河畔的丘陵，坐在樹蔭下",
        "今天也有花如昨日般盛開",
        "我們連呼吸都忘了",
        "甚至連眨眼都嫌麻煩",
        "這陣花散的風暴",
        "正是春天的小偷",
        "今天的時光隨風流逝",
        "甚至站起來都嫌麻煩",
        "在花間隙中，藍天散落",
        "尚未結束的春日飄雪",
        "今日也去見你",
        "坐在樹蔭下",
        "吐出一口嘆息",
        "花期也將結束",
        "明天也會去見你",
        "春天已將結束",
        "時間也如餘韻般飄散",
        "若以愛歌頌，詞句不足",
        "連押韻都嫌麻煩",
        "盛開的此刻豈是言語能描述的",
        "輕輕地，我們連聲音都忘了",
        "甚至連眨眼都嫌麻煩",
        "賞花的就只有我們",
        "不要凋謝啊，春日飄雪",
        "再多一會兒",
        "還能數得過來",
        "還剩兩朵花",
        "僅剩一朵花",
        "最後只剩下樹葉，輕輕地",
        "此刻，春日終結"
      ]
    }    
  },
  {
    "id": 22,
    "title": "風を食む",
    "artist": "ヨルシカ",
    "album": "創作(Type A)",
    "release": "2021/1/27",
    "img": "./images/22.jpg",
    "popularity": 64073,
    "lyrics":{
      "japanese": [
        "{明日|あした}はきっと{天気|てんき}で {悪|わる}いことなんてないね",
        "タイムカードを{押|お}して{僕|ぼく}は{朝|あさ} {目|め}を{開|ひら}いた",
        "{僕|ぼく}らは{今日|きょう}も{買|か}ってる {足|た}りないものしかなくて",
        "{靴|くつ}を{履|は}きながら{空想|くうそう} {空|そら}は{高|たか}いのかな",
        "{貴方|あなた}さえ {貴方|あなた}さえ",
        "これはきっとわからないんだ",
        "{微笑|はにか}む{顔|かお}が{散|ち}らつく",
        "{口|くち}を{開|あ}けて{風|かぜ}を{食|は}む",
        "{春|はる}が{先|さき} {花ぐわし|はなぐわし}",
        "{桜|さくら}の{散|ち}りぬるを{眺|なが}む",
        "{今|いま} {風|かぜ}を{食|は}む",
        "{棚|たな}の{心|こころ}は{十五円|じゅうごえん} {一|ひと}つだけ{売|う}れ{残|のこ}った",
        "{値引|ねび}きのシールを{貼|は}って{閉店時間|へいてんじかん}を{待|ま}った",
        "{明日|あした}もきっと{天気|てんき}で {此処|ここ}にも{客|きゃく}が{並|なら}んで",
        "{二割引|にわりびき}の{心|こころ}は{誰|だれ}かが{買|か}うんだろうか",
        "{貴方|あなた}だけ {貴方|あなた}だけ",
        "{僕|ぼく}はずっと{想|おも}ってたんだ",
        "ただ{白|しろ}いあの{雲|くも}を{待|ま}つ",
        "{風|かぜ}のない{春|はる}に{騒|さわ}めく",
        "{草流|くさなが}れ {天飛|あまと}ぶや",
        "{軽|かる}く{花|はな}の{散|ち}るを{眺|なが}む",
        "{今|いま} {風|かぜ}を{食|は}む",
        "ついに{心|こころ}は{半額|はんがく} {何時|いつ}までも{売|う}れ{残|のこ}って",
        "テレビを{眺|なが}めて{空想|くうそう} ニュースは{希望|きぼう}のバーゲン",
        "{貴方|あなた}は{今日|きょう}も{買|か}ってる {足|た}りないものしかなくて",
        "{俯|うつむ}く{手元|てもと}で{購入|こうにゅう} {空|そら}は{高|たか}いのかな",
        "{貴方|あなた}だけ {貴方|あなた}だけ",
        "この{希望|きぼう}をわからないんだ",
        "{売|う}れ{残|のこ}りの{心|こころ}でいい",
        "{僕|ぼく}にとっては{美|うつく}しい",
        "{春|はる}が{咲|さ}き {花ぐわし|はなぐわし}",
        "{桜|さくら}の{散|ち}りぬるを{眺|なが}む",
        "{貴方|あなた}しか {貴方|あなた}しか",
        "{貴方|あなた}の{傷|きず}はわからないんだ",
        "{口|くち}を{開|あ}けて{歌|うた}い{出|だ}す",
        "{今|いま} {貴方|あなた}は{風|かぜ}を{食|は}む",
        "{冬籠|ふゆごも}り {春|はる}が{先|さき}",
        "{貴方|あなた}の{歌|うた}だけが{聞|き}こえる",
        "{今|いま} {口遊|くちずさ}む{貴方|あなた}だけ",
        "{貴方|あなた}だけ ({貴方|あなた}だけ {貴方|あなた}だけ)"
      ],
      "chinese": [
        "明天一定會放晴，壞事也都不見了吧",
        "打卡上班，我睜開了眼睛迎接早晨",
        "我們今天也在買東西，只因什麼都缺少",
        "穿鞋時想著，天空是否遙遠",
        "唯有你，唯有你",
        "或許永遠都無法理解",
        "你微笑的臉龐浮現眼前",
        "張開嘴巴啜飲微風",
        "春天已至，花香四溢",
        "望著櫻花飄落",
        "此刻，啜飲微風",
        "貨架上的心價值十五元，只有一件滯銷品",
        "貼上打折標籤，等待關店時刻",
        "明天也一定會放晴，這裡也將排滿客人",
        "打八折的心，是否會有人購買",
        "唯有你，唯有你",
        "我一直在想著",
        "只是等待那片白雲",
        "在無風的春天掀起騷動",
        "青草流動，天空飛翔",
        "輕輕望著花瓣飄落",
        "此刻，啜飲微風",
        "最終心變成半價，永遠滯銷",
        "望著電視發呆，新聞報導著希望大拍賣",
        "今天你依然在購買，什麼都缺少",
        "低頭購物時想著，天空是否遙遠",
        "唯有你，唯有你",
        "無法理解這份希望",
        "滯銷的心也無妨",
        "對我來說它美麗無比",
        "春天綻放，花香四溢",
        "望著櫻花飄落",
        "唯有你，唯有你",
        "無法理解你的傷痕",
        "張開嘴巴唱出歌聲",
        "此刻你在啜飲微風",
        "冬藏結束，春天到來",
        "唯有你的歌聲傳來",
        "此刻，哼唱的唯有你",
        "唯有你 (唯有你 唯有你)"
      ]
    }    
  },
  {
    "id": 23,
    "title": "花に亡霊",
    "artist": "ヨルシカ",
    "album": "盗作",
    "release": "2020/7/29",
    "img": "./images/23.jpg",
    "popularity": 84107,
    "lyrics":{
      "japanese": [
        "もう{忘|わす}れてしまったかな",
        "{夏|なつ}の{木陰|こかげ}に{座|すわ}ったまま {氷菓|ひょうか}を{口|くち}に{放|ほう}り{込|こ}んで{風|かぜ}を{待|ま}っていた",
        "もう{忘|わす}れてしまったかな {世|よ}の{中|なか}の{全部|ぜんぶ}{嘘|うそ}だらけ",
        "{本当|ほんとう}の{価値|かち}を{二人|ふたり}で{探|さが}しに{行|い}こうと{笑|わら}ったこと",
        "{忘|わす}れないように {色褪|いろあ}せないように",
        "{形|かたち}に{残|のこ}るものが{全|すべ}てじゃないように",
        "{言葉|ことば}をもっと{教|おし}えて {夏|なつ}が{来|く}るって{教|おし}えて",
        "{僕|ぼく}は{描|えが}いてる {眼|め}に{映|うつ}ったのは{夏|なつ}の{亡霊|ぼうれい}だ",
        "{風|かぜ}にスカートが{揺|ゆ}れて {想|おも}い{出|で}なんて{忘|わす}れて",
        "{浅|あさ}い{呼吸|こきゅう}をする {汗|あせ}を{拭|ぬぐ}って{夏|なつ}めく",
        "もう{忘|わす}れてしまったかな",
        "{夏|なつ}の{木陰|こかげ}に{座|すわ}った{頃|ころ} {遠|とお}くの{丘|おか}から{顔出|かおだ}した{雲|くも}があったじゃないか",
        "{君|きみ}はそれを{掴|つか}もうとして {馬鹿|ばか}みたいに{空|そら}を{切|き}った{手|て}で",
        "{僕|ぼく}は{紙|かみ}に{雲|くも}{一|ひと}つを{書|か}いて {笑|わら}って{握|にぎ}って{見|み}せて",
        "{忘|わす}れないように {色褪|いろあ}せないように",
        "{歴史|れきし}に{残|のこ}るものが{全|すべ}てじゃないから",
        "{今|いま}だけ{顔|かお}も{失|な}くして {言葉|ことば}も{全部|ぜんぶ}{忘|わす}れて",
        "{君|きみ}は{笑|わら}ってる {夏|なつ}を{待|ま}っている{僕|ぼく}ら{亡霊|ぼうれい}だ",
        "{心|こころ}をもっと{教|おし}えて {夏|なつ}の{匂|にお}いを{教|おし}えて",
        "{浅|あさ}い{呼吸|こきゅう}をする",
        "{忘|わす}れないように {色褪|いろあ}せないように",
        "{心|こころ}に{響|ひび}くものが{全|すべ}てじゃないから",
        "{言葉|ことば}をもっと{教|おし}えて さよならだって{教|おし}えて",
        "{今|いま}も{見|み}るんだよ {夏|なつ}に{咲|さ}いてる{花|はな}に{亡霊|ぼうれい}を",
        "{言葉|ことば}じゃなくて{時間|じかん}を {時間|じかん}じゃなくて{心|こころ}を",
        "{浅|あさ}い{呼吸|こきゅう}をする {汗|あせ}を{拭|ぬぐ}って{夏|なつ}めく",
        "{夏|なつ}の{匂|にお}いがする",
        "もう{忘|わす}れてしまったかな",
        "{夏|なつ}の{木陰|こかげ}に{座|すわ}ったまま {氷菓|ひょうか}を{口|くち}に{放|ほう}り{込|こ}んで{風|かぜ}を{待|ま}っていた"
      ],
      "chinese": [
        "已經忘記了嗎",
        "坐在夏日的樹蔭下，將冰淇淋放入口中，等待微風",
        "已經忘記了嗎，這世間充滿了謊言",
        "曾說過要一起尋找真正的價值，笑著說過",
        "為了不忘記，為了不褪色",
        "並非所有留下形狀的東西都是一切",
        "請告訴我更多的話語，告訴我夏天即將到來",
        "我在描繪，映入眼中的乃是夏日的亡靈",
        "裙擺隨風搖曳，拋開回憶",
        "淺淺呼吸，擦去汗水，迎接夏日",
        "已經忘記了嗎",
        "坐在夏日的樹蔭下的時候，不遠的山丘上浮現的雲彩，不是嗎",
        "你試圖抓住它，那樣愚蠢地撲向天空",
        "我在紙上畫了一朵雲，笑著緊握展示給你看",
        "為了不忘記，為了不褪色",
        "並非歷史上留下的東西才是全部",
        "此時此刻，暫且拋去面容，拋開所有的言語",
        "你在笑，我們是等待夏日的亡靈",
        "請教我更多心靈的話語，告訴我夏天的氣息",
        "淺淺呼吸",
        "為了不忘記，為了不褪色",
        "並非所有在心中迴響的才是全部",
        "請教我更多的話語，甚至告訴我再見",
        "我依然看著，在夏日盛開的花中見到亡靈",
        "不是言語而是時間，不是時間而是心靈",
        "淺淺呼吸，擦去汗水，迎接夏日",
        "聞到夏天的氣息",
        "已經忘記了嗎",
        "坐在夏日的樹蔭下，將冰淇淋放入口中，等待微風"
      ]
    }    
  },
  {
    "id": 24,
    "title": "憂一乗",
    "artist": "ヨルシカ",
    "album": "エルマ",
    "release": "2019/8/28",
    "img": "./images/24.jpg",
    "popularity": 40163,
    "lyrics":{
      "japanese": [
        "{湖|みずうみ}の{底|そこ}にいるみたいだ",
        "{呼吸|こきゅう}の{一|ひと}つが{喉|のど}に{絡|から}んだ",
        "{気泡|きほう}を{吐|は}き{出|だ}して{数秒|すうびょう} やっと{足|あし}が{着|つ}いた",
        "{柔|やわ}らかな{泥|どろ}の{感触|かんしょく}がした",
        "ずっとずっとずっとずっとずっと",
        "{君|きみ}を{追|お}っているだけで",
        "{何|どう}しようもないことばかり{言|い}いたかった",
        "{睡蓮|すいれん}が{浮|う}いていた {水圧|すいあつ}で{透明|とうめい}だ",
        "もう{蜃気楼|しんきろう}よりも{確|たし}かならそれでいいよ",
        "{適当|てきとう}でもいいから {目的|もくてき}とかいいから",
        "このまま{何処|どこ}でもいいからさ {逃|に}げよう",
        "{湖|みずうみ}の{底|そこ}にいるみたいだ",
        "{濡|ぬ}れる{鼓膜|こまく}がくすぐったいんだ",
        "{期待|きたい}も{将来|しょうらい}も{明日|あした}も{何|なに}も{聞|き}きたくなかった",
        "{口|くち}から{溢|あふ}れる{泡|あわ}ぶくが{綺麗|きれい}で",
        "ずっとずっとずっとずっとずっと",
        "{見惚|みほ}れてしまっただけで",
        "{心|こころ}より{大事|だいじ}なものを{見|み}つけたかった",
        "{言葉|ことば}って{薄情|はくじょう}だ {水圧|すいあつ}で{透明|とうめい}だ",
        "なぁ {建前|たてまえ}より{綺麗|きれい}なものを{探|さが}してるんだ",
        "そんなの{忘|わす}れていいからもう {逃|に}げよう",
        "こんな{自分|じぶん}ならいらない {僕|ぼく}には{何|なに}にもいらない",
        "{お金|おかね}も{名声|めいせい}も{愛|あい}も{称賛|しょうさん}も{何|なに}にもいらない",
        "このまま{遠|とお}くに{行|い}きたい {思|おも}い{出|で}の{外|そと}に{触|ふ}れたい",
        "また{君|きみ}の{歌|うた}が{聴|き}きたい",
        "ずっとずっとずっとずっとずっと",
        "{君|きみ}を{追|お}っているだけで",
        "{何|どう}しようもないことだけ{歌|うた}いたかった",
        "{睡蓮|すいれん}が{浮|う}いていた {水圧|すいあつ}で{透明|とうめい}だ",
        "もう{蜃気楼|しんきろう}よりも{確|たし}かならそれでいいよ",
        "このまま{何処|どこ}でもいいからさ",
        "{本当|ほんとう}は{全部|ぜんぶ}{置|お}いてただ{逃|に}げ{出|だ}したいだけだった",
        "{人生|じんせい}は{透明|とうめい}だ {水圧|すいあつ}で{透明|とうめい}だ",
        "もう{蜃気楼|しんきろう}よりも{確|たし}かならそれでいいよ",
        "{適当|てきとう}でもいいから {目的|もくてき}とかいいから",
        "このまま{何処|どこ}でもいいからさ {逃|に}げよう"
      ],
      "chinese": [
        "就像置身於湖底",
        "一口呼吸卡在喉嚨裡",
        "吐出氣泡數秒後，終於觸到地面",
        "感受到柔軟的泥土觸感",
        "一直一直一直一直一直",
        "只因追隨著你",
        "我總想說些無可奈何的話",
        "睡蓮漂浮著，在水壓下顯得透明",
        "如果比海市蜃樓還確定，那樣就好",
        "隨便也沒關係，不需要什麼目的",
        "就這樣，去任何地方吧，逃跑吧",
        "就像置身於湖底",
        "濕潤的鼓膜有些癢癢的",
        "不想聽任何期待、未來或明天",
        "口中溢出的泡沫那樣美麗",
        "一直一直一直一直一直",
        "只因著迷於它",
        "想找到比心更重要的東西",
        "言語是如此無情，在水壓下顯得透明",
        "啊，尋找比虛偽更美麗的東西",
        "可以忘掉那些了，逃跑吧",
        "這樣的自己不需要，什麼也不需要",
        "金錢、名聲、愛情、讚美，什麼都不需要",
        "只想這樣去到遠方，觸碰回憶之外",
        "還想再聽到你的歌聲",
        "一直一直一直一直一直",
        "只因追隨著你",
        "只想唱那些無法改變的事",
        "睡蓮漂浮著，在水壓下顯得透明",
        "如果比海市蜃樓還確定，那樣就好",
        "就這樣，去任何地方吧",
        "其實我只是想放下一切逃跑",
        "人生是透明的，在水壓下顯得透明",
        "如果比海市蜃樓還確定，那樣就好",
        "隨便也沒關係，不需要什麼目的",
        "就這樣，去任何地方吧，逃跑吧"
      ]
    }    
  },
  {
    "id": 25,
    "title": "藍二乗",
    "artist": "ヨルシカ",
    "album": "だから僕は音楽を辞めた",
    "release": "2019/4/10",
    "img": "./images/25.jpg",
    "popularity": 19213,
    "lyrics":{
      "japanese": [
        "{変|か}わらない{風景|ふうけい} {浅|あさ}い{正午|しょうご}",
        "{高架下|こうかした}、{藍二乗|あいにじょう}、{寝転|ねころ}ぶまま",
        "{白紙|はくし}の{人生|じんせい}に{拍手|はくしゅ}の{音|おと}が{一|ひと}つ{鳴|な}っている",
        "{空|から}っぽな{自分|じぶん}を{今日|きょう}も{歌|うた}っていた",
        "{変|か}わらないように",
        "{君|きみ}が{主役|しゅやく}のプロットを{書|か}くノートの{中|なか}",
        "{止|と}まったガス{水道|すいどう} {世間|せけん}もニュースも{所詮|しょせん}{他人事|たにんごと}",
        "この{人生|じんせい}さえほら、インクみたいだ",
        "あの{頃|ころ}ずっと{頭|あたま}に{描|えが}いた{夢|ゆめ}も{大人|おとな}になるほど{時効|じこう}になっていく",
        "ただ、ただ{雲|くも}を{見上|みあ}げても",
        "{視界|しかい}は{今日|きょう}も{流|なが}れるまま",
        "{遠|とお}く{仰|あお}いだ{夜|よる}に{花泳|はなおよ}ぐ",
        "{春|はる}と{見紛|みまが}うほどに",
        "{君|きみ}をただ{見失|みうしな}うように",
        "{転|ころ}ばないように{下|した}を{向|む}いた",
        "{人生|じんせい}はどうにも{妥協|だきょう}で{出来|でき}てる",
        "{心|こころ}も{運命|うんめい}もラブソングも{人生|じんせい}も{信|しん}じない",
        "{所詮|しょせん}{売|う}れないなら{全部|ぜんぶ}が{無駄|むだ}だ",
        "{敢|わざ}と{零|こぼ}した{夢|ゆめ}で{描|えが}いた{今|いま}に{寝|ね}そべったままで{時効|じこう}を{待|ま}っている",
        "ただ、ただ{目蓋|まぶた}の{裏側|うらがわ}",
        "{遠|とお}く{描|えが}く{君|きみ}を{見|み}たまま",
        "ノート、{薄|うす}い{夜隅|よすみ}に{花泳|はなおよ}ぐ",
        "{僕|ぼく}の{目|め}にまた{一|ひと}つ",
        "{人生|じんせい}は{妥協|だきょう}の{連続|れんぞく}なんだ",
        "そんなこと{疾|とう}にわかってたんだ",
        "エルマ、{君|きみ}なんだよ",
        "{君|きみ}だけが{僕|ぼく}の{音楽|おんがく}なんだ",
        "この{詩|し}はあと{八十字|はちじゅうじ}",
        "{人生|じんせい}の{価値|かち}は、{終|お}わり{方|かた}だろうから",
        "ただ、ただ{君|きみ}だけを{描|えが}け",
        "{視界|しかい}の{藍|あい}も{滲|にじ}んだまま",
        "{遠|とお}く{仰|あお}いだ{空|そら}に{花泳|はなおよ}ぐ",
        "この{目覆|めおお}う{藍二乗|あいにじょう}",
        "ただ、ただ",
        "{遠|とお}く{仰|あお}いだ{空|そら}、{君|きみ}が{涼|すず}む",
        "ただ{夜|よる}を{泳|およ}ぐように"
      ],
      "chinese": [
        "不變的風景，淺淺的正午",
        "高架下，藍色平方，躺在地上",
        "在白紙般的人生上，響起了一聲掌聲",
        "今天也歌唱著空虛的自己",
        "為了不要改變",
        "在記錄著以你為主角的劇本的筆記中",
        "停止的瓦斯、水道，世間和新聞畢竟都是別人的事",
        "甚至這人生，仿佛也像墨水",
        "那時腦中描繪的夢想，隨著成長逐漸過期",
        "只是，只是仰望著雲彩",
        "視線今天依然在流動",
        "遠遠仰望夜空中浮動的花朵",
        "彷彿讓人誤以為是春天",
        "只感覺逐漸失去了你",
        "低著頭不敢跌倒",
        "人生充滿妥協",
        "不相信心靈、命運、情歌或人生",
        "畢竟賣不出去就全是無用",
        "故意讓夢想落空，躺在此刻的時光裡等待過期",
        "只是，只是眼皮的背後",
        "遙望著遠方描繪的你",
        "筆記、薄薄的夜角裡花朵游動",
        "在我的眼裡又多了一朵",
        "人生就是不斷的妥協",
        "早已明白了這一點",
        "艾瑪，是你啊",
        "你是我的音樂",
        "這首詩還剩八十字",
        "人生的價值，在於結尾",
        "只是，只是描繪著你",
        "視界的藍色也開始模糊",
        "遠遠仰望天空中浮動的花朵",
        "覆蓋我雙眼的藍色平方",
        "只是，只是",
        "遠遠仰望天空，你在涼爽的微風中",
        "只是像在夜裡游泳一樣"
      ]
    }    
  },
  {
    "id": 26,
    "title": "だから僕は音楽を辞めた",
    "artist": "ヨルシカ",
    "album": "だから僕は音楽を辞めた",
    "release": "2019/4/10",
    "img": "./images/26.jpg",
    "popularity": 95885,
    "lyrics":{
      "japanese": [
        "{考|かんが}えたってわからないし",
        "{青空|あおぞら}の{下|した}、{君|きみ}を{待|ま}った",
        "{風|かぜ}が{吹|ふ}いた{正午|しょうご}、{昼下|ひるさ}がりを{抜|ぬ}け{出|だ}す{想像|そうぞう}",
        "ねぇ、これからどうなるんだろうね",
        "{進|すす}め{方|かた}{教|おそ}わらないんだよ",
        "{君|きみ}の{目|め}を{見|み}た {何|なに}も{言|い}えず{僕|ぼく}は{歩|ある}いた",
        "{考|かんが}えたってわからないし",
        "{青春|せいしゅん}なんてつまらないし",
        "{辞|や}めた{筈|はず}のピアノ、{机|つくえ}を{弾|ひ}く{癖|くせ}が{抜|ぬ}けない",
        "ねぇ、{将来|しょうらい}{何|なに}してるだろうね",
        "{音楽|おんがく}はしてないといいね",
        "{困|こま}らないでよ",
        "{心|こころ}の{中|なか}に{一|ひと}つ{線|せん}を{引|ひ}いても",
        "{何時|どう}しても{消|き}えなかった {今更|いまさら}なんだから",
        "なぁ、もう{思|おも}い{出|だ}すな",
        "{間違|まちが}ってるんだよ",
        "{分|わ}かってないよ、あんたら{人間|にんげん}も",
        "{本当|ほんとう}も{愛|あい}も{世界|せかい}も{苦|くる}しさも{人生|じんせい}もどうでもいいよ",
        "{正|ただ}しいかどうか{知|し}りたいのだって{防衛本能|ぼうえいほんのう}だ",
        "{考|かんが}えたんだ あんたのせいだ",
        "{考|かんが}えたってわからないが、{本当|ほんとう}に{年老|としお}いたくないんだ",
        "{何時|いつ}か{死|し}んだらって{思|おも}うだけで{胸|むね}が{空|から}っぽになるんだ",
        "{将来|しょうらい}{何|なに}してるだろうって",
        "{大人|おとな}になったらわかったよ",
        "{何|なに}もしてないさ",
        "{幸|しあわ}せな{顔|かお}した{人|ひと}が{憎|にく}いのは",
        "{何|どう}わり{切|き}ったらいいんだ",
        "{満|み}たされない{頭|あたま}の{奥|おく}の",
        "{化|ば}け{物|もの}みたいな{劣等感|れっとうかん}",
        "{間違|まちが}ってないよ",
        "なぁ、{何|なん}だかんだあんたら{人間|にんげん}だ",
        "{愛|あい}も{救|すく}いも{優|やさ}しさも{根拠|こんきょ}がないなんて{気味|きみ}が{悪|わる}いよ",
        "ラブソングなんかが{痛|いた}いのだって{防衛本能|ぼうえいほんのう}だ",
        "{何|どう}でもいいか あんたのせいだ",
        "{考|かんが}えたってわからないし",
        "{生|い}きてるだけでも{苦|くる}しいし",
        "{音楽|おんがく}とか{儲|もう}からないし",
        "{歌詞|かし}とか{適当|てきとう}でもいいよ",
        "{何|どう}でもいいんだ",
        "{間違|まちが}ってないだろ",
        "{間違|まちが}ってないよな",
        "{間違|まちが}ってないよな",
        "{間違|まちが}ってるんだよ {分|わ}かってるんだ",
        "あんたら{人間|にんげん}も",
        "{本当|ほんとう}も{愛|あい}も{救|すく}いも{優|やさ}しさも{人生|じんせい}もどうでもいいんだ",
        "{正|ただ}しい{答|こた}えが{言|い}えないのだって{防衛本能|ぼうえいほんのう}だ",
        "{何|どう}でもいいや あんたのせいだ",
        "{僕|ぼく}だって{信念|しんねん}があった",
        "{今|いま}じゃ{塵|ちり}みたいな{想|おも}いだ",
        "{何度|なんど}でも{君|きみ}を{書|か}いた",
        "{売|う}れることこそがどうでもよかったんだ",
        "{本当|ほんとう}だ {本当|ほんとう}なんだ {昔|むかし}はそうだった",
        "だから{僕|ぼく}は",
        "だから{僕|ぼく}は{音楽|おんがく}を{辞|や}めた"
      ],
      "chinese": [
        "思考也無法理解",
        "在藍天下等待著你",
        "正午微風拂過，幻想著脫離午後的寂靜",
        "嘿，接下來會怎樣呢",
        "沒有人教我該如何前進",
        "看著你的眼睛，卻無話可說，我邁步而行",
        "思考也無法理解",
        "青春無聊透頂",
        "戒掉的鋼琴，卻改不了敲桌子的習慣",
        "嘿，將來會做些什麼呢",
        "最好別做音樂吧",
        "別為難我",
        "即使在心中畫下一道線",
        "還是無法抹去，畢竟已經太遲了",
        "喂，別再回憶了",
        "這是錯的",
        "你們人類不懂啊",
        "真實、愛、世界、痛苦和人生怎樣都無所謂",
        "想知道正確與否只是出於防衛本能",
        "我思考過，都是你的錯",
        "思考也無法理解，但我真的不想變老",
        "光是想到有朝一日會死，胸口便感到空虛",
        "將來會做些什麼呢",
        "長大之後明白了",
        "什麼都沒有做",
        "為何厭惡那些臉上掛著幸福的人",
        "該怎麼解釋才好",
        "頭腦深處的",
        "如怪物般的自卑感",
        "我沒錯",
        "喂，不管怎樣你們也是人類",
        "愛、救贖和溫柔全都毫無根據，真令人不安",
        "覺得情歌刺耳也是防衛本能",
        "無所謂，都是你的錯",
        "思考也無法理解",
        "僅僅活著就感到痛苦",
        "音樂也賺不到錢",
        "歌詞隨便點也無妨",
        "怎樣都好",
        "這沒錯吧",
        "沒錯吧",
        "沒錯吧",
        "這是錯的，我知道的",
        "你們人類也是",
        "真實、愛、救贖、溫柔和人生怎樣都無所謂",
        "說不出正確答案也是防衛本能",
        "無所謂了，都是你的錯",
        "我曾經也有信念",
        "如今它就像塵埃一樣",
        "無數次寫下你",
        "銷量根本無所謂",
        "這是真的，真的，以前是這樣的",
        "所以我",
        "所以我放棄了音樂"
      ]
    }    
  },
  {
    "id": 27,
    "title": "言って。",
    "artist": "ヨルシカ",
    "album": "夏草が邪魔をする",
    "release": "2017/6/28",
    "img": "./images/27.jpg",
    "popularity": 39508
  },
  {
    "id": 28,
    "title": "雲と幽霊",
    "artist": "ヨルシカ",
    "album": "夏草が邪魔をする",
    "release": "2017/6/28",
    "img": "./images/28.jpg",
    "popularity": 50999
  },
  {
    "id": 29,
    "title": "靴の花火",
    "artist": "ヨルシカ",
    "album": "夏草が邪魔をする",
    "release": "2017/6/28",
    "img": "./images/29.jpg",
    "popularity": 42304
  },
  {
    "id": 30,
    "title": "地球儀",
    "artist": "米津玄師",
    "album": "地球儀",
    "release": "2023/7/26",
    "img": "./images/30.jpg",
    "popularity": 48560
  },
  {
    "id": 31,
    "title": "KICK BACK",
    "artist": "米津玄師",
    "album": "KICK BACK",
    "release": "2022/11/23",
    "img": "./images/31.jpg",
    "popularity": 77814
  },
  {
    "id": 32,
    "title": "M八七",
    "artist": "米津玄師",
    "album": "M八七",
    "release": "2022/7/10",
    "img": "./images/32.jpg",
    "popularity": 97502
  },
  {
    "id": 33,
    "title": "Pale Blue",
    "artist": "米津玄師",
    "album": "Pale Blue",
    "release": "2021/6/16",
    "img": "./images/33.jpg",
    "popularity": 57000
  },
  {
    "id": 34,
    "title": "死神",
    "artist": "米津玄師",
    "album": "Pale Blue",
    "release": "2021/6/16",
    "img": "./images/34.jpg",
    "popularity": 47127
  },
  {
    "id": 35,
    "title": "馬と鹿",
    "artist": "米津玄師",
    "album": "馬と鹿",
    "release": "2019/9/11",
    "img": "./images/35.jpg",
    "popularity": 16413
  },
  {
    "id": 36,
    "title": "海の幽霊",
    "artist": "米津玄師",
    "album": "馬と鹿",
    "release": "2019/9/11",
    "img": "./images/36.jpg",
    "popularity": 4328
  },
  {
    "id": 37,
    "title": "Lemon",
    "artist": "米津玄師",
    "album": "Lemon",
    "release": "2018/3/14",
    "img": "./images/37.jpg",
    "popularity": 6107
  },
  {
    "id": 38,
    "title": "orion",
    "artist": "米津玄師",
    "album": "orion",
    "release": "2017/2/15",
    "img": "./images/38.jpg",
    "popularity": 73726
  },
  {
    "id": 39,
    "title": "LOSER",
    "artist": "米津玄師",
    "album": "LOSER/ナンバーナイン",
    "release": "2016/9/28",
    "img": "./images/39.jpg",
    "popularity": 41867
  },
  {
    "id": 40,
    "title": "SPECIALZ",
    "artist": "King Gnu",
    "album": "SPECIALZ",
    "release": "2023/9/6",
    "img": "./images/40.jpg",
    "popularity": 31783
  },
  {
    "id": 41,
    "title": "雨燦々",
    "artist": "King Gnu",
    "album": "Stardom",
    "release": "2022/11/30",
    "img": "./images/41.jpg",
    "popularity": 37372
  },
  {
    "id": 42,
    "title": "カメレオン",
    "artist": "King Gnu",
    "album": "カメレオン",
    "release": "2022/3/16",
    "img": "./images/42.jpg",
    "popularity": 29500
  },
  {
    "id": 43,
    "title": "一途",
    "artist": "King Gnu",
    "album": "一途/逆夢",
    "release": "2021/12/29",
    "img": "./images/43.jpg",
    "popularity": 90118
  },
  {
    "id": 44,
    "title": "逆夢",
    "artist": "King Gnu",
    "album": "一途/逆夢",
    "release": "2021/12/29",
    "img": "./images/44.jpg",
    "popularity": 51443
  },
  {
    "id": 45,
    "title": "Prayer X",
    "artist": "King Gnu",
    "album": "Prayer X",
    "release": "2018/9/19",
    "img": "./images/45.jpg",
    "popularity": 93569
  },
  {
    "id": 46,
    "title": "Teenager Forever",
    "artist": "King Gnu",
    "album": "CEREMONY",
    "release": "2020/1/15",
    "img": "./images/46.jpg",
    "popularity": 84719
  },
  {
    "id": 47,
    "title": "白日",
    "artist": "King Gnu",
    "album": "CEREMONY",
    "release": "2020/1/15",
    "img": "./images/47.jpg",
    "popularity": 39076
  },
  {
    "id": 48,
    "title": "Cantabile",
    "artist": "Novelbright",
    "album": "CIRCUS",
    "release": "2024/4/3",
    "img": "./images/48.jpg",
    "popularity": 37770
  },
  {
    "id": 49,
    "title": "雪の音",
    "artist": "Novelbright",
    "album": "CIRCUS",
    "release": "2024/4/3",
    "img": "./images/49.jpg",
    "popularity": 14690
  },
  {
    "id": 50,
    "title": "愛とか恋とか",
    "artist": "Novelbright",
    "album": "Assort",
    "release": "2022/5/18",
    "img": "./images/50.jpg",
    "popularity": 26840
  },
  {
    "id": 51,
    "title": "開幕宣言",
    "artist": "Novelbright",
    "album": "開幕宣言",
    "release": "2021/4/28",
    "img": "./images/51.jpg",
    "popularity": 49516
  },
  {
    "id": 52,
    "title": "Sunny drop",
    "artist": "Novelbright",
    "album": "開幕宣言",
    "release": "2021/4/28",
    "img": "./images/52.jpg",
    "popularity": 19518
  },
  {
    "id": 53,
    "title": "ツキミソウ",
    "artist": "Novelbright",
    "album": "開幕宣言",
    "release": "2021/4/28",
    "img": "./images/53.jpg",
    "popularity": 84851
  },
  {
    "id": 54,
    "title": "夢花火",
    "artist": "Novelbright",
    "album": "WONDERLAND",
    "release": "2020/5/27",
    "img": "./images/54.jpg",
    "popularity": 15052
  },
  {
    "id": 55,
    "title": "Chessboard",
    "artist": "Official髭男dism",
    "album": "Chessboard/日常",
    "release": "2023/9/13",
    "img": "./images/55.jpg",
    "popularity": 74367
  },
  {
    "id": 56,
    "title": "ミックスナッツ",
    "artist": "Official髭男dism",
    "album": "ミックスナッツ EP",
    "release": "2022/6/22",
    "img": "./images/56.jpg",
    "popularity": 26687
  },
  {
    "id": 57,
    "title": "I LOVE...",
    "artist": "Official髭男dism",
    "album": "I LOVE...",
    "release": "2020/2/12",
    "img": "./images/57.jpg",
    "popularity": 83331
  },
  {
    "id": 58,
    "title": "宿命",
    "artist": "Official髭男dism",
    "album": "宿命",
    "release": "2019/7/31",
    "img": "./images/58.jpg",
    "popularity": 20954
  },
  {
    "id": 59,
    "title": "Pretender",
    "artist": "Official髭男dism",
    "album": "Pretender",
    "release": "2019/5/15",
    "img": "./images/59.jpg",
    "popularity": 27831
  },
  {
    "id": 60,
    "title": "Sharon",
    "artist": "Official髭男dism",
    "album": "Rejoice",
    "release": "2024/7/31",
    "img": "./images/60.jpg",
    "popularity": 43360
  },
  {
    "id": 61,
    "title": "SOULSOUP",
    "artist": "Official髭男dism",
    "album": "Rejoice",
    "release": "2024/7/31",
    "img": "./images/61.jpg",
    "popularity": 19574
  },
  {
    "id": 62,
    "title": "Cry Baby",
    "artist": "Official髭男dism",
    "album": "Editorial",
    "release": "2021/8/18",
    "img": "./images/62.jpg",
    "popularity": 74405
  },
  {
    "id": 63,
    "title": "Laughter",
    "artist": "Official髭男dism",
    "album": "Editorial",
    "release": "2021/8/18",
    "img": "./images/63.jpg",
    "popularity": 69778
  },
  {
    "id": 64,
    "title": "イエスタデイ",
    "artist": "Official髭男dism",
    "album": "Traveler",
    "release": "2019/10/9",
    "img": "./images/64.jpg",
    "popularity": 87943
  },
  {
    "id": 65,
    "title": "裸の勇者",
    "artist": "Vaundy",
    "album": "裸の勇者",
    "release": "2022/2/23",
    "img": "./images/65.jpg",
    "popularity": 62224
  },
  {
    "id": 66,
    "title": "灯火",
    "artist": "Vaundy",
    "album": "strobo",
    "release": "2020/5/27",
    "img": "./images/66.jpg",
    "popularity": 59594
  },
  {
    "id": 67,
    "title": "怪獣の花唄",
    "artist": "Vaundy",
    "album": "strobo",
    "release": "2020/5/27",
    "img": "./images/67.jpg",
    "popularity": 91074
  },
  {
    "id": 68,
    "title": "東京フラッシュ",
    "artist": "Vaundy",
    "album": "strobo",
    "release": "2020/5/27",
    "img": "./images/68.jpg",
    "popularity": 15257
  },
  {
    "id": 69,
    "title": "不可幸力",
    "artist": "Vaundy",
    "album": "strobo",
    "release": "2020/5/27",
    "img": "./images/69.jpg",
    "popularity": 28306
  },
  {
    "id": 70,
    "title": "僕は今日も",
    "artist": "Vaundy",
    "album": "strobo",
    "release": "2020/5/27",
    "img": "./images/70.jpg",
    "popularity": 98680
  },
  {
    "id": 71,
    "title": "世界の秘密",
    "artist": "Vaundy",
    "album": "replica",
    "release": "2023/11/15",
    "img": "./images/71.jpg",
    "popularity": 42494
  },
  {
    "id": 72,
    "title": "そんなbitterな話",
    "artist": "Vaundy",
    "album": "replica",
    "release": "2023/11/15",
    "img": "./images/72.jpg",
    "popularity": 21493
  },
  {
    "id": 73,
    "title": "花占い",
    "artist": "Vaundy",
    "album": "replica",
    "release": "2023/11/15",
    "img": "./images/73.jpg",
    "popularity": 80336
  },
  {
    "id": 74,
    "title": "CHAINSAW BLOOD",
    "artist": "Vaundy",
    "album": "replica",
    "release": "2023/11/15",
    "img": "./images/74.jpg",
    "popularity": 30515
  },
  {
    "id": 75,
    "title": "踊",
    "artist": "Ado",
    "album": "狂言",
    "release": "2022/1/26",
    "img": "./images/75.jpg",
    "popularity": 3585
  },
  {
    "id": 76,
    "title": "ギラギラ",
    "artist": "Ado",
    "album": "狂言",
    "release": "2022/1/26",
    "img": "./images/76.jpg",
    "popularity": 21067
  },
  {
    "id": 77,
    "title": "うっせぇわ",
    "artist": "Ado",
    "album": "狂言",
    "release": "2022/1/26",
    "img": "./images/77.jpg",
    "popularity": 11549
  },
  {
    "id": 78,
    "title": "新時代",
    "artist": "Ado",
    "album": "ウタの歌 ONE PIECE FILM RED",
    "release": "2023/6/14",
    "img": "./images/78.jpg",
    "popularity": 62394
  },
  {
    "id": 79,
    "title": "私は最強",
    "artist": "Ado",
    "album": "ウタの歌 ONE PIECE FILM RED",
    "release": "2023/6/14",
    "img": "./images/79.jpg",
    "popularity": 25069
  },
  {
    "id": 80,
    "title": "逆光",
    "artist": "Ado",
    "album": "ウタの歌 ONE PIECE FILM RED",
    "release": "2023/6/14",
    "img": "./images/80.jpg",
    "popularity": 45164
  },
  {
    "id": 81,
    "title": "Tot Musica",
    "artist": "Ado",
    "album": "ウタの歌 ONE PIECE FILM RED",
    "release": "2023/6/14",
    "img": "./images/81.jpg",
    "popularity": 34340
  },
  {
    "id": 82,
    "title": "向日葵",
    "artist": "Ado",
    "album": "残夢",
    "release": "2024/7/10",
    "img": "./images/82.jpg",
    "popularity": 52643
  },
  {
    "id": 83,
    "title": "永遠のあくる日",
    "artist": "Ado",
    "album": "残夢",
    "release": "2024/7/11",
    "img": "./images/83.jpg",
    "popularity": 63680
  },
  {
    "id": 84,
    "title": "唱",
    "artist": "Ado",
    "album": "残夢",
    "release": "2024/7/12",
    "img": "./images/84.jpg",
    "popularity": 31840
  },
  {
    "id": 85,
    "title": "何なんw",
    "artist": "藤井風",
    "album": "HELP EVER HURT NEVER",
    "release": "2020/5/20",
    "img": "./images/85.jpg",
    "popularity": 92698
  },
  {
    "id": 86,
    "title": "優しさ",
    "artist": "藤井風",
    "album": "HELP EVER HURT NEVER",
    "release": "2020/5/20",
    "img": "./images/86.jpg",
    "popularity": 94329
  },
  {
    "id": 87,
    "title": "死ぬのがいいわ",
    "artist": "藤井風",
    "album": "HELP EVER HURT NEVER",
    "release": "2020/5/20",
    "img": "./images/87.jpg",
    "popularity": 3491
  },
  {
    "id": 88,
    "title": "帰ろう",
    "artist": "藤井風",
    "album": "HELP EVER HURT NEVER",
    "release": "2020/5/20",
    "img": "./images/88.jpg",
    "popularity": 3365
  },
  {
    "id": 89,
    "title": "きらり",
    "artist": "藤井風",
    "album": "LOVE ALL SERVE ALL",
    "release": "2022/3/23",
    "img": "./images/89.jpg",
    "popularity": 45295
  },
  {
    "id": 90,
    "title": "燃えよ",
    "artist": "藤井風",
    "album": "LOVE ALL SERVE ALL",
    "release": "2022/3/23",
    "img": "./images/90.jpg",
    "popularity": 18484
  },
  {
    "id": 91,
    "title": "旅路",
    "artist": "藤井風",
    "album": "LOVE ALL SERVE ALL",
    "release": "2022/3/23",
    "img": "./images/91.jpg",
    "popularity": 52985
  },
  {
    "id": 92,
    "title": "Motivation",
    "artist": "???",
    "album": "???",
    "release": "???",
    "img": "./images/92.jpg",
    "popularity": 90000
  }
]